{"@schemaLocation": "http://www.loc.gov/mods/v3 http://www.loc.gov/standards/mods/v3/mods-3-6.xsd", "titleInfo": {"title": "High-footed basin (British Museum, G.66)"}, "typeOfResource": "still image", "genre": "ceramics", "originInfo": {"place": {"placeTerm": "Iznik, Bursa, Turkey ; Nicaea (anc.)"}, "dateOther": {"@keyDate": "yes", "#text": "ca. 1545-1550"}, "dateCreated": [{"@point": "start", "#text": "1545"}, {"@point": "end", "#text": "1550"}, "ca. 1545-1550"]}, "physicalDescription": {"extent": "h: 27.3 cm; d: 42 cm"}, "abstract": "Composite lotuses and saz leaves, lobed medallions, double prunus stems, roundel, flowers.", "subject": [{"topic": "Islamic art"}, {"topic": "ceramics"}, {"topic": "bowls"}, {"topic": "İznik designs"}], "extension": [{"styleWrap": {"style": "Ottoman"}}, {"cultureWrap": {"culture": "Islamic"}}, {"cultureWrap": {"culture": "Turkish"}}, {"indexingMaterialsTechSet": {"termMaterialsTech": "pottery"}}, {"indexingMaterialsTechSet": {"termMaterialsTech": "glaze"}}, {"indexingMaterialsTechSet": {"termMaterialsTech": "underglazing"}}, {"DRSMetadata": {"inDRS": "true", "accessFlag": "P", "contentModel": "STILL IMAGE", "uriType": "IDS", "fileDeliveryURL": "https://nrs.harvard.edu/urn-3:FHCL:27735598", "ownerCode": "FHCL.FAL", "ownerCodeDisplayName": "Fine Arts Library", "lastModifiedDate": "2016-07-25T18:42:10.699Z"}}, {"librarycloud": {"availableTo": "Everyone", "digitalFormats": {"digitalFormat": "Images"}, "originalDocument": "https://s3.amazonaws.com/via-presto/prod/olvwork223991.xml", "processingDate": "2019-11-23T17:38Z"}}], "location": [{"physicalLocation": {"@type": "repository", "#text": "British Museum, London, England"}, "shelfLocator": "G.66"}, {"url": {"@displayLabel": "Harvard Digital Collections", "@access": "object in context", "#text": "https://id.lib.harvard.edu/digital_collections/W223991_urn-3:FHCL:27735598"}}], "relatedItem": [{"@type": "constituent", "titleInfo": {"title": "Full view"}, "typeOfResource": "still image", "note": "Funding for this image is provided by the Aga Khan Program and the Stuart Cary Welch Islamic and South Asian Photograph Collection. ", "classification": null, "location": [{"url": [{"@displayLabel": "Full Image", "@note": "unrestricted", "@access": "raw object", "#text": "https://nrs.harvard.edu/urn-3:FHCL:27735598"}, {"@displayLabel": "Thumbnail", "@access": "preview", "#text": "https://nrs.harvard.edu/urn-3:FHCL:27735598?width=150&height=150&usethumb=y"}]}, {"physicalLocation": {"@valueURI": "http://isni.org/isni/0000000109432246", "@displayLabel": "Harvard repository", "@type": "repository", "#text": "Fine Arts Library, Special Collections, Harvard University"}, "shelfLocator": "SCW2016.02646"}], "recordInfo": {"recordIdentifier": "16199392"}, "extension": {"HarvardRepositories": {"HarvardRepository": "Fine Arts"}}}, {"@otherType": "HOLLIS Images record", "location": {"url": "https://id.lib.harvard.edu/images/olvwork223991/urn-3:FHCL:27735598/catalog"}}], "recordInfo": {"recordContentSource": [{"@authority": "marcorg", "#text": "MH"}, {"@authority": "marcorg", "#text": "MH-VIA"}], "recordChangeDate": {"@encoding": "iso8601", "#text": "20190701"}, "recordIdentifier": {"@source": "MH:VIA", "#text": "W223991_urn-3:FHCL:27735598"}, "languageOfCataloging": {"languageTerm": "eng"}}, "language": {"languageTerm": [{"@type": "code", "#text": "zxx"}, {"@type": "text", "#text": "No linguistic content"}]}, "iiif_manifest": "https://iiif.lib.harvard.edu/manifests/ids:423185877"}