<oai_dc:dc xmlns:xsi="http://www.w3.org/2001/XMLSchema-instance" xmlns:dc="http://purl.org/dc/elements/1.1/" xmlns:oai_dc="http://www.openarchives.org/OAI/2.0/oai_dc/" xmlns="http://www.openarchives.org/OAI/2.0/" xsi:schemaLocation="http://www.openarchives.org/OAI/2.0/oai_dc/ http://www.openarchives.org/OAI/2.0/oai_dc.xsd">
            <dc:title>[Farm&#257;ns] : manuscript, 1910?</dc:title>
            <dc:creator>Aga Khan , 1877-1957</dc:creator>
            <dc:type>Text</dc:type>
            <dc:date>1910</dc:date>
            <dc:publisher>Microforms, Lamont Library, Harvard University Houghton Library, Harvard University Master Microforms, Harvard University Microforms, Lamont Library, Harvard University Master Microforms, Harvard University Houghton Library, Harvard University Microforms, Lamont Library, Harvard University Master Microforms, Harvard University Houghton Library, Harvard University Master Microforms, Harvard University Microforms, Lamont Library, Harvard University Houghton Library, Harvard University Master Microforms, Harvard University Microforms, Lamont Library, Harvard University Houghton Library, Harvard University Houghton Library, Harvard University Microforms, Lamont Library, Harvard University Master Microforms, Harvard University Master Microforms, Harvard University Microforms, Lamont Library, Harvard University Houghton Library, Harvard University Microforms, Lamont Library, Harvard University Master Microforms, Harvard University Houghton Library, Harvard University Microforms, Lamont Library, Harvard University Houghton Library, Harvard University Master Microforms, Harvard University Houghton Library, Harvard University Microforms, Lamont Library, Harvard University Master Microforms, Harvard University</dc:publisher>
            <dc:language>inc Indic languages</dc:language>
            <dc:format>print</dc:format>
            <dc:format>1 v. (140 leaves)</dc:format>
            <dc:description>According to a note on p. 1, contains farm&#257;ns made by Im&#257;m Sul&#7789;&#257;n Mu&#7717;ammad Sh&#257;h [Aga Khan III] at Zanzibar, Bagamoyo and Dar es Salaam. The manuscript records those farm&#257;ns made between 19 Je&#7789;h [Jyeshtha] to 23 Bhadr [Bhadrapad] s. 1956 (approx. May-September 1899).</dc:description>
            <dc:description>Title provided by cataloger.</dc:description>
            <dc:description>Local paper. Pages generally in good condition, though slightly brittle; binding disintegrating.</dc:description>
            <dc:description>23 x 20 cm. (19 x 17cm.).</dc:description>
            <dc:description>Written in black ink, 13-14 lines per page.</dc:description>
            <dc:description>Pamphlet binding in poor condition; single section sewn through fold, leather guards on inside fold. Lacks covers.</dc:description>
            <dc:description>MS Indic 2534. Houghton Library, Harvard University.</dc:description>
            <dc:description>In Sindhi in Khojki script.</dc:description>
            <dc:subject>South Asian literature</dc:subject>
            <dc:subject>Religious literature, Indic</dc:subject>
            <dc:subject>Ismaili literature</dc:subject>
            <dc:subject>Indic literature</dc:subject>
            <dc:subject>Islamic sects</dc:subject>
            <dc:subject>Ismailites</dc:subject>
            <dc:relation>https://id.lib.harvard.edu/alma/990119191800203941/catalog</dc:relation>
            <dc:identifier>https://nrs.harvard.edu/urn-3:FHCL:3153225</dc:identifier>
            <dc:identifier>https://ids.lib.harvard.edu/ids/view/13697272?width=150&amp;height=150&amp;usethumb=y</dc:identifier>
            <dc:identifier>https://id.lib.harvard.edu/curiosity/islamic-heritage-project/40-990119191800203941</dc:identifier>
            <dc:identifier>https://id.lib.harvard.edu/digital_collections/990119191800203941</dc:identifier>
         </oai_dc:dc>
      
