{"thumbnail": "https://iiif.princeton.edu/loris/figgy_prod/a1%2Fd8%2Ff6%2Fa1d8f63d9a1e4579ba08fb09cc0a1269%2Fintermediate_file.jp2/full/!200,150/0/default.jpg", "director": "ناصر حسين", "date_created": "1980", "extent": "1 piece.", "genre": "Posters", "identifier": "sf2686", "resource_type": "still image", "title": "عمل ايه الحب في بابا", "language": "ara", "local_identifier": "eg1-0976", "geographic_origin": "Egypt", "member_of_collections": "Selections from the Near East Collections", "rendered_actors": "يونس شلبي"}