<record xmlns="http://www.openarchives.org/OAI/2.0/" xmlns:xsi="http://www.w3.org/2001/XMLSchema-instance" xmlns:xlink="http://www.w3.org/1999/xlink"><header><identifier>81055/vdc_100024054395.0x00000a_en</identifier><datestamp>2019-10-15T21:31:08.878Z</datestamp></header><metadata><mods xmlns="http://www.loc.gov/mods/v3"><identifier>81055/vdc_100024054395.0x00000a_en</identifier><location><shelfLocator>IOR/R/15/1/32, ff 16v-17</shelfLocator><url>http://www.qdl.qa/en/archive/81055/vdc_100024054395.0x00000a</url><url access="preview">https://images.qdl.qa/iiif/images/81055/vdc_100000000193.0x000005/IOR_R_15_1_32_0033.jp2/full/!1000,1000/0/default.jpg</url><physicalLocation>British Library: India Office Records and Private Papers</physicalLocation></location><recordInfo><recordIdentifer>IOR/R/15/1/32, ff 16v-17</recordIdentifer></recordInfo><titleInfo><title>Letter No. 10: Ephraim Gerrish Stannus, Resident in the Persian Gulf, Bushire, to William Newnham, Chief Secretary to Government, Bombay</title></titleInfo><originInfo><dateIssued>1824/1824</dateIssued><dateCaptured>2014-10-23T00:15:06</dateCaptured></originInfo><language><languageTerm authority="iso639-2b">eng</languageTerm></language><physicalDescription><extent>2 folios</extent></physicalDescription><abstract>In this letter Ephraim Gerrish Stannus, Resident in the Persian Gulf, Bushire, relays intelligence concerning a skirmish which took place in Aboothabee [Abu Dhabi] between troops recruited from the Mornaseer [Manasir] tribe by Mahomed bin Shakhboot [Muhammad bin Shakhbut Al Nahayan, former Shaikh of Abu Dhabi] and forces deployed by his brother, Tahnoon bin Shakhboot [Tahnun bin Shakhbut, Shaikh of Abu Dhabi]. Stannus reports that Mahomed bin Shakhboot's troops, amounting to around 400 men, were defeated by his brother's force of 1300 men.</abstract><typeOfResource>text</typeOfResource><genre type="class">Archival item</genre><accessCondition type="Use and reproduction" xlink:href="http://www.qdl.qa/en/archive/81055/vdc_100024054395.0x00000a#share">Open Government Licence</accessCondition></mods></metadata></record>