<record xmlns="http://www.openarchives.org/OAI/2.0/" xmlns:xsi="http://www.w3.org/2001/XMLSchema-instance" xmlns:xlink="http://www.w3.org/1999/xlink"><header><identifier>81055/vdc_100024054665.0x00000e_ar</identifier><datestamp>2019-10-15T21:36:05.279Z</datestamp></header><metadata><mods xmlns="http://www.loc.gov/mods/v3"><identifier>81055/vdc_100024054665.0x00000e_ar</identifier><location><shelfLocator>IOR/R/15/1/33, ff 16v-19</shelfLocator><url>http://www.qdl.qa/%D8%A7%D9%84%D8%B9%D8%B1%D8%A8%D9%8A%D8%A9/archive/81055/vdc_100024054665.0x00000e</url><url access="preview">https://images.qdl.qa/iiif/images/81055/vdc_100000000193.0x000006/IOR_R_15_1_33_0039.jp2/full/!1000,1000/0/default.jpg</url><physicalLocation>المكتبة البريطانية: أوراق خاصة وسجلات من مكتب الهند</physicalLocation></location><recordInfo><recordIdentifer>IOR/R/15/1/33, ff 16v-19</recordIdentifer></recordInfo><titleInfo><title>رسالة رقم ٤٦ من إفرايم جريش ستانوس، المقيم البريطاني في الخليج العربي في شيراز، إلى ويليام نيونام، السكرتير الأول للحكومة، الإدارة السياسية، بومباي</title></titleInfo><originInfo><dateIssued>1824/1824</dateIssued><dateCaptured>2014-10-01T01:14:43</dateCaptured></originInfo><language><languageTerm authority="iso639-2b">eng</languageTerm></language><physicalDescription><extent>٤ أوراق</extent></physicalDescription><accessCondition type="Use and reproduction" xlink:href="http://www.qdl.qa/%D8%A7%D9%84%D8%B9%D8%B1%D8%A8%D9%8A%D8%A9/archive/81055/vdc_100024054665.0x00000e#share">رخصة حكومة مفتوحة</accessCondition></mods></metadata></record>