{"objectID":321647,"isHighlight":false,"accessionNumber":"86.11.27","isPublicDomain":true,"primaryImage":"https://images.metmuseum.org/CRDImages/an/original/ss86_11_27gp.jpg","primaryImageSmall":"https://images.metmuseum.org/CRDImages/an/web-large/ss86_11_27gp.jpg","additionalImages":[],"constituents":null,"department":"Ancient Near Eastern Art","objectName":"Stamp seal","title":"Scaraboid seal with peaked back","culture":"Babylonian (?)","period":"Neo-Babylonian (?)","dynasty":"","reign":"","portfolio":"","artistRole":"","artistPrefix":"","artistDisplayName":"","artistDisplayBio":"","artistSuffix":"","artistAlphaSort":"","artistNationality":"","artistBeginDate":"","artistEndDate":"","objectDate":"ca. 6th–4th century B.C.","objectBeginDate":-600,"objectEndDate":-300,"medium":"Sard, red","dimensions":"Diameter: 1.38 cm\r\nHeight: 1.27 cm\r\nString Hole: 0.34-0.45 cm","creditLine":"Purchase, 1886","geographyType":"","city":"","state":"","county":"","country":"","region":"Iran or Mesopotamia","subregion":"","locale":"","locus":"","excavation":"","river":"","classification":"Stone-Stamp Seals","rightsAndReproduction":"","linkResource":"","metadataDate":"2019-03-11T12:39:20.717Z","repository":"Metropolitan Museum of Art, New York, NY","objectURL":"https://www.metmuseum.org/art/collection/search/321647","tags":["Seals"]}