{"objectID":322373,"isHighlight":false,"accessionNumber":"01.25.7","isPublicDomain":true,"primaryImage":"https://images.metmuseum.org/CRDImages/an/original/51583.jpg","primaryImageSmall":"https://images.metmuseum.org/CRDImages/an/web-large/51583.jpg","additionalImages":[],"constituents":null,"department":"Ancient Near Eastern Art","objectName":"Funerary relief","title":"Funerary relief","culture":"","period":"","dynasty":"","reign":"","portfolio":"","artistRole":"","artistPrefix":"","artistDisplayName":"","artistDisplayBio":"","artistSuffix":"","artistAlphaSort":"","artistNationality":"","artistBeginDate":"","artistEndDate":"","objectDate":"ca. 50–150","objectBeginDate":50,"objectEndDate":150,"medium":"Limestone","dimensions":"10.55 x 9.57 in. (26.8 x 24.31 cm)","creditLine":"Purchase, 1901","geographyType":"From","city":"","state":"","county":"","country":"","region":"Syria","subregion":"Palmyra","locale":"","locus":"","excavation":"","river":"","classification":"Stone-Sculpture","rightsAndReproduction":"","linkResource":"","metadataDate":"2019-03-11T12:32:34.67Z","repository":"Metropolitan Museum of Art, New York, NY","objectURL":"https://www.metmuseum.org/art/collection/search/322373","tags":["Heads","Men"]}