{"objectID":322583,"isHighlight":false,"accessionNumber":"30.112.44","isPublicDomain":true,"primaryImage":"https://images.metmuseum.org/CRDImages/an/original/me30_112_44.jpg","primaryImageSmall":"https://images.metmuseum.org/CRDImages/an/web-large/me30_112_44.jpg","additionalImages":[],"constituents":null,"department":"Ancient Near Eastern Art","objectName":"Jar","title":"Jar","culture":"Sasanian","period":"Sasanian","dynasty":"","reign":"","portfolio":"","artistRole":"","artistPrefix":"","artistDisplayName":"","artistDisplayBio":"","artistSuffix":"","artistAlphaSort":"","artistNationality":"","artistBeginDate":"","artistEndDate":"","objectDate":"ca. 3rd–4th century A.D.","objectBeginDate":200,"objectEndDate":400,"medium":"Ceramic","dimensions":"16.77 in. (42.6 cm)","creditLine":"Purchase, V. Everit Macy Gift, 1930","geographyType":"","city":"","state":"","county":"","country":"","region":"Mesopotamia","subregion":"said to be from Tekrit","locale":"","locus":"","excavation":"","river":"","classification":"Ceramics-Vessels","rightsAndReproduction":"","linkResource":"","metadataDate":"2019-03-11T12:42:11.25Z","repository":"Metropolitan Museum of Art, New York, NY","objectURL":"https://www.metmuseum.org/art/collection/search/322583","tags":["Jars"]}