{"objectID":323766,"isHighlight":false,"accessionNumber":"41.160.201","isPublicDomain":true,"primaryImage":"https://images.metmuseum.org/CRDImages/an/original/DP271923.jpg","primaryImageSmall":"https://images.metmuseum.org/CRDImages/an/web-large/DP271923.jpg","additionalImages":[],"constituents":null,"department":"Ancient Near Eastern Art","objectName":"Vessel","title":"Fragment of a vessel with wheat stalks and a procession of bulls in relief","culture":"","period":"Late Uruk–Jemdet Nasr","dynasty":"","reign":"","portfolio":"","artistRole":"","artistPrefix":"","artistDisplayName":"","artistDisplayBio":"","artistSuffix":"","artistAlphaSort":"","artistNationality":"","artistBeginDate":"","artistEndDate":"","objectDate":"ca. 3300–2900 B.C.","objectBeginDate":-3300,"objectEndDate":-2900,"medium":"Limestone","dimensions":"W. 17.2 cm (6 3/4 in.)","creditLine":"Bequest of W. Gedney Beatty, 1941","geographyType":"","city":"","state":"","county":"","country":"","region":"Southern Mesopotamia","subregion":"","locale":"","locus":"","excavation":"","river":"","classification":"Stone-Vessels","rightsAndReproduction":"","linkResource":"","metadataDate":"2019-03-11T12:34:10.497Z","repository":"Metropolitan Museum of Art, New York, NY","objectURL":"https://www.metmuseum.org/art/collection/search/323766","tags":["Bulls"]}