{"objectID":323982,"isHighlight":false,"accessionNumber":"43.102.22","isPublicDomain":true,"primaryImage":"https://images.metmuseum.org/CRDImages/an/original/ME43_102_22.jpg","primaryImageSmall":"https://images.metmuseum.org/CRDImages/an/web-large/ME43_102_22.jpg","additionalImages":[],"constituents":null,"department":"Ancient Near Eastern Art","objectName":"Pin","title":"Pin","culture":"Iran","period":"Iron Age II","dynasty":"","reign":"","portfolio":"","artistRole":"","artistPrefix":"","artistDisplayName":"","artistDisplayBio":"","artistSuffix":"","artistAlphaSort":"","artistNationality":"","artistBeginDate":"","artistEndDate":"","objectDate":"ca. 8th–7th century B.C.","objectBeginDate":-800,"objectEndDate":-600,"medium":"Bronze","dimensions":"3 3/16 x 7/16 x 5/8 in. (8.1 x 1.1 x 1.6 cm)","creditLine":"Rogers Fund, 1943","geographyType":"","city":"","state":"","county":"","country":"","region":"Iran, Luristan","subregion":"Surkh Dum","locale":"","locus":"","excavation":"","river":"","classification":"Metalwork-Ornaments","rightsAndReproduction":"","linkResource":"","metadataDate":"2019-03-11T12:29:46.607Z","repository":"Metropolitan Museum of Art, New York, NY","objectURL":"https://www.metmuseum.org/art/collection/search/323982","tags":["Pins"]}