{"objectID":324127,"isHighlight":false,"accessionNumber":"51.25.13","isPublicDomain":true,"primaryImage":"https://images.metmuseum.org/CRDImages/an/original/DP270683.jpg","primaryImageSmall":"https://images.metmuseum.org/CRDImages/an/web-large/DP270683.jpg","additionalImages":["https://images.metmuseum.org/CRDImages/an/original/DP273770.jpg"],"constituents":null,"department":"Ancient Near Eastern Art","objectName":"Vessel","title":"Vessel","culture":"","period":"Early Dynastic II (?)","dynasty":"","reign":"","portfolio":"","artistRole":"","artistPrefix":"","artistDisplayName":"","artistDisplayBio":"","artistSuffix":"","artistAlphaSort":"","artistNationality":"","artistBeginDate":"","artistEndDate":"","objectDate":"ca. 2700–2600 B.C. (?)","objectBeginDate":-2700,"objectEndDate":-2600,"medium":"Ceramic","dimensions":"H. 29.9 cm (11 3/4 in.)","creditLine":"Rogers Fund and Gifts of Lucy W. Drexel, Theodore M. Davis, Helen Miller Gould, Albert Gallatin, Egypt Exploration Fund and Egyptian Research Account, by exchange, 1950","geographyType":"","city":"","state":"","county":"","country":"","region":"Mesopotamia, Diyala region","subregion":"","locale":"","locus":"","excavation":"","river":"","classification":"Ceramics-Vessels","rightsAndReproduction":"","linkResource":"","metadataDate":"2019-03-11T12:24:25.31Z","repository":"Metropolitan Museum of Art, New York, NY","objectURL":"https://www.metmuseum.org/art/collection/search/324127","tags":["Utilitarian Objects"]}