{"objectID":325017,"isHighlight":false,"accessionNumber":"60.20.28","isPublicDomain":true,"primaryImage":"https://images.metmuseum.org/CRDImages/an/original/ME60_20_28.jpg","primaryImageSmall":"https://images.metmuseum.org/CRDImages/an/web-large/ME60_20_28.jpg","additionalImages":[],"constituents":null,"department":"Ancient Near Eastern Art","objectName":"Bracelet","title":"Bracelet","culture":"Iran","period":"Iron Age II","dynasty":"","reign":"","portfolio":"","artistRole":"","artistPrefix":"","artistDisplayName":"","artistDisplayBio":"","artistSuffix":"","artistAlphaSort":"","artistNationality":"","artistBeginDate":"","artistEndDate":"","objectDate":"ca. 9th century B.C.","objectBeginDate":-900,"objectEndDate":-800,"medium":"Bronze","dimensions":"1.77 x 2.8 in. (4.5 x 7.11 cm)","creditLine":"Rogers Fund, 1960","geographyType":"","city":"","state":"","county":"","country":"","region":"Iran","subregion":"Hasanlu","locale":"","locus":"","excavation":"","river":"","classification":"Metalwork-Ornaments","rightsAndReproduction":"","linkResource":"","metadataDate":"2019-03-11T12:34:21.34Z","repository":"Metropolitan Museum of Art, New York, NY","objectURL":"https://www.metmuseum.org/art/collection/search/325017","tags":["Bracelets"]}