{"objectID":325234,"isHighlight":false,"accessionNumber":"62.40.15","isPublicDomain":true,"primaryImage":"https://images.metmuseum.org/CRDImages/an/original/ME62_40_15.jpg","primaryImageSmall":"https://images.metmuseum.org/CRDImages/an/web-large/ME62_40_15.jpg","additionalImages":[],"constituents":null,"department":"Ancient Near Eastern Art","objectName":"Arrowhead","title":"Arrowhead","culture":"Iran","period":"Iron Age","dynasty":"","reign":"","portfolio":"","artistRole":"","artistPrefix":"","artistDisplayName":"","artistDisplayBio":"","artistSuffix":"","artistAlphaSort":"","artistNationality":"","artistBeginDate":"","artistEndDate":"","objectDate":"2nd–1st millennium B.C.","objectBeginDate":-2000,"objectEndDate":-1,"medium":"Bronze","dimensions":"0.63 x 2.44 in. (1.6 x 6.2 cm)","creditLine":"Gift of Jerome M. Eisenberg, 1962","geographyType":"","city":"","state":"","county":"","country":"","region":"Iran","subregion":"","locale":"","locus":"","excavation":"","river":"","classification":"Metalwork-Implements","rightsAndReproduction":"","linkResource":"","metadataDate":"2019-03-11T12:40:41.31Z","repository":"Metropolitan Museum of Art, New York, NY","objectURL":"https://www.metmuseum.org/art/collection/search/325234","tags":["Arrowheads"]}