{"objectID":327256,"isHighlight":false,"accessionNumber":"1986.311.53","isPublicDomain":true,"primaryImage":"https://images.metmuseum.org/CRDImages/an/original/ss1986_311_53.jpg","primaryImageSmall":"https://images.metmuseum.org/CRDImages/an/web-large/ss1986_311_53.jpg","additionalImages":[],"constituents":null,"department":"Ancient Near Eastern Art","objectName":"Cylinder seal","title":"Cylinder seal","culture":"Elamite","period":"Neo-Elamite","dynasty":"","reign":"","portfolio":"","artistRole":"","artistPrefix":"","artistDisplayName":"","artistDisplayBio":"","artistSuffix":"","artistAlphaSort":"","artistNationality":"","artistBeginDate":"","artistEndDate":"","objectDate":"early 1st millennium B.C.","objectBeginDate":-1000,"objectEndDate":-539,"medium":"Stone","dimensions":"0.98 in. (2.49 cm)","creditLine":"Gift of Martin and Sarah Cherkasky, 1986","geographyType":"","city":"","state":"","county":"","country":"","region":"Iran","subregion":"","locale":"","locus":"","excavation":"","river":"","classification":"Stone-Cylinder Seals","rightsAndReproduction":"","linkResource":"","metadataDate":"2019-03-11T12:21:32.09Z","repository":"Metropolitan Museum of Art, New York, NY","objectURL":"https://www.metmuseum.org/art/collection/search/327256","tags":["Animals","Seals"]}