{"objectID":327358,"isHighlight":false,"accessionNumber":"1988.102.34","isPublicDomain":true,"primaryImage":"https://images.metmuseum.org/CRDImages/an/original/sd1988_102_34.jpg","primaryImageSmall":"https://images.metmuseum.org/CRDImages/an/web-large/sd1988_102_34.jpg","additionalImages":[],"constituents":null,"department":"Ancient Near Eastern Art","objectName":"Jar","title":"Spouted jar with a frieze of ibexes","culture":"Iran","period":"Iron Age","dynasty":"","reign":"","portfolio":"","artistRole":"","artistPrefix":"","artistDisplayName":"","artistDisplayBio":"","artistSuffix":"","artistAlphaSort":"","artistNationality":"","artistBeginDate":"","artistEndDate":"","objectDate":"ca. early 1st millennium B.C.","objectBeginDate":-1000,"objectEndDate":-1,"medium":"Ceramic, paint","dimensions":"8.82 x 9.53 in. (22.4 x 24.21 cm)","creditLine":"Gift of Ernest Erickson Foundation, 1988","geographyType":"","city":"","state":"","county":"","country":"","region":"Iran, probably from Luristan","subregion":"","locale":"","locus":"","excavation":"","river":"","classification":"Ceramics-Vessels","rightsAndReproduction":"","linkResource":"","metadataDate":"2019-03-11T12:30:47.043Z","repository":"Metropolitan Museum of Art, New York, NY","objectURL":"https://www.metmuseum.org/art/collection/search/327358","tags":["Goats","Jars"]}