{"objectID":327576,"isHighlight":false,"accessionNumber":"1999.153.28a, b","isPublicDomain":true,"primaryImage":"https://images.metmuseum.org/CRDImages/an/original/sd1999_153_28.jpg","primaryImageSmall":"https://images.metmuseum.org/CRDImages/an/web-large/sd1999_153_28.jpg","additionalImages":[],"constituents":null,"department":"Ancient Near Eastern Art","objectName":"Leather","title":"Length of leather with V-shaped design on one side","culture":"","period":"Six Dynasties Period","dynasty":"","reign":"","portfolio":"","artistRole":"","artistPrefix":"","artistDisplayName":"","artistDisplayBio":"","artistSuffix":"","artistAlphaSort":"","artistNationality":"","artistBeginDate":"","artistEndDate":"","objectDate":"ca. 8th century A.D.","objectBeginDate":700,"objectEndDate":800,"medium":"Leather","dimensions":"5 in. (12.7 cm)","creditLine":"Gift of Jacqueline Simcox, 1999","geographyType":"","city":"","state":"","county":"","country":"","region":"Caucasus region","subregion":"","locale":"","locus":"","excavation":"","river":"","classification":"Textiles-Costumes","rightsAndReproduction":"","linkResource":"","metadataDate":"2019-03-11T12:31:00.403Z","repository":"Metropolitan Museum of Art, New York, NY","objectURL":"https://www.metmuseum.org/art/collection/search/327576","tags":["Textile Fragments"]}