{"objectID":327613,"isHighlight":false,"accessionNumber":"1999.325.17","isPublicDomain":true,"primaryImage":"https://images.metmuseum.org/CRDImages/an/original/1999,325,017.jpg","primaryImageSmall":"https://images.metmuseum.org/CRDImages/an/web-large/1999,325,017.jpg","additionalImages":[],"constituents":null,"department":"Ancient Near Eastern Art","objectName":"Cylinder seal","title":"Cylinder seal","culture":"Babylonian","period":"Old Babylonian","dynasty":"","reign":"","portfolio":"","artistRole":"","artistPrefix":"","artistDisplayName":"","artistDisplayBio":"","artistSuffix":"","artistAlphaSort":"","artistNationality":"","artistBeginDate":"","artistEndDate":"","objectDate":"ca. early 2nd millennium B.C.","objectBeginDate":-2000,"objectEndDate":-1000,"medium":"Hematite","dimensions":"H. 15/16 in. (2.4 cm);  Diam. 3/8 in. (1.0 cm)","creditLine":"Gift of Nanette B. Kelekian, in memory of Charles Dikran and Beatrice Kelekian, 1999","geographyType":"","city":"","state":"","county":"","country":"","region":"Mesopotamia","subregion":"","locale":"","locus":"","excavation":"","river":"","classification":"Stone-Cylinder Seals-Inscribed","rightsAndReproduction":"","linkResource":"","metadataDate":"2019-03-11T12:35:52.56Z","repository":"Metropolitan Museum of Art, New York, NY","objectURL":"https://www.metmuseum.org/art/collection/search/327613","tags":["Men","Seals"]}