{"thumbnail": "https://iiif.princeton.edu/loris/figgy_prod/b6%2F69%2F61%2Fb66961e2adbe4e57844ac7b32d7e4207%2Fintermediate_file.jp2/full/!200,150/0/default.jpg", "description": "ff. 51. 204 x 122; 144 x 61 mm. 21 lin. 18th cen. Brockelmann, GAL, I, 548 (commentary 1, gloss b); S I, 759. Incip.: ... أما بعد حمد الله لمستأهله ... قال الشارح النحرىر عامله الله بلطفه الخطىر ... الحمد لله اقول فى تعقىب التسمىة بالتجمىد اقتداء باسلوب الکتاب المجىد", "author": "Khayālī, Aḥmad ibn Mūsá, -1457?", "identifier": "http://arks.princeton.edu/ark:/88435/c821gn41s", "alternate_identifier": "http://arks.princeton.edu/ark:/88435/c821gn41s", "replaces": "pudl0112/6267136", "title": "Ḥāshiyah ʻalá sharḥ al-Taftāzānī.", "type": "Early works to 1800", "creator": "Khayālī, Aḥmad ibn Mūsá, -1457?", "date": "1700-1799", "language": "Arabic", "local identifier": "p2z10z369t", "subject": "Taftāzānī, Masʻūd ibn ʻUmar, 1322-1389?—Sharḥ al-ʻAqāʼid al-Nasafīyah", "source metadata identifier": "6267136", "call number": "Electronic Resource", "member of collections": "Princeton Digital Library of Islamic Manuscripts"}