{"thumbnail": "https://iiif.princeton.edu/loris/figgy_prod/8f%2F30%2F22%2F8f30222ca853462b91bedbbdf5a9b28d%2Fintermediate_file.jp2/full/!200,150/0/default.jpg", "description": "ff. 177 [acephalous]. Iṣfahān, Dhū al-ḥijjah 1096H., Bāqir ibn Hāshim al-Gīlānī. Brockelmann, GAL, l, 674 (no. 38); SI, 930; Mach, R. Yahuda, 4870.", "author": "Ṭūsī, Naṣīr al-Dīn Muḥammad ibn Muḥammad, 1201-1274", "identifier": "http://arks.princeton.edu/ark:/88435/dj52w7977", "alternate_identifier": "http://arks.princeton.edu/ark:/88435/dj52w7977", "title": "Taḥrīr al-Mijistī.", "type": "Early works to 1800", "creator": "Ṭūsī, Naṣīr al-Dīn Muḥammad ibn Muḥammad, 1201-1274", "date": "1600-1699", "language": "Arabic", "subject": "Astronomy, Arab—Early works to 1800", "source metadata identifier": "6124208", "call number": "Electronic Resource", "member of collections": "Princeton Digital Library of Islamic Manuscripts"}