{"thumbnail": "https://iiif.princeton.edu/loris/figgy_prod/ec%2F5e%2Fdd%2Fec5edd0a42c740609e36acaaafc2a040%2Fintermediate_file.jp2/full/!200,150/0/default.jpg", "description": "ff. 115. 194 x 136; 137 x 80 mm. 17 lin. Shaʻbān 1072; on fol. la ownership note of Muḥammad Ṣādiq ibn Muṣṭafá Shānīzādah. Deals with ṣalāt al-musāfirīn and various legal aspects of travel and military expeditions; the title appears in red on fol. 2b, but in a slightly different form in the preface, where the author says (fol. 2a paenult.): وسمىته کتابا مرعىا لاحکام المقىمىن ومرضىا برهانا لارباب المسافرىن Incip.: ... الحمد لله ... وبعد فىقول ... سألنى بعض الساىرىن من المسافرىن عن حقىقة صلوة الاتمام للمقىمىن وصلوة القصر للمسافرىن", "author": "Rūmī, Ibrāhīm ibn ʻUmar", "identifier": "http://arks.princeton.edu/ark:/88435/pr76f603h", "alternate_identifier": "http://arks.princeton.edu/ark:/88435/pr76f603h", "replaces": "pudl0112/6265247", "title": "Murʻī lil-muqīmīn wa-murḍī lil-musāfirīn.", "type": "Early works to 1800", "creator": "Rūmī, Ibrāhīm ibn ʻUmar", "date": "1600-1699", "language": "Arabic", "local_identifier": "pqb98nz051", "subject": "Travel (Islamic law)—Early works to 1800", "source_metadata_identifier": "6265247", "call_number": "Electronic Resource", "member_of_collections": "Princeton Digital Library of Islamic Manuscripts"}