{"number_oclc": ["43538315"], "item": {"digital_id": ["https://hdl.loc.gov/loc.amed/amedscd.2004433197"], "call_number": ["BT1410 .S26 1926"], "language": ["per"], "contributors": ["Ṣanʻatīʹzādah Kirmānī, author."], "title": "Dāstān-i Mānī-i naqqāsh", "notes": ["Early imprint.", "In Persian."], "format": ["text"], "subjects": ["Mani,--active 3rd century", "Manichaeism", "Iran"], "date": "1926", "created_published": ["[Tehran?] : Maṭbaʻah-ʼi Shūravī, 1305 [1926 or 1927]"], "medium": ["116 pages : illustrations ; 25 cm"], "other_title": ["داستان مانى نقاش /"]}, "access_restricted": false, "number": ["2004433197", "43538315", "2020-03-04t14:30:05"], "original_format": ["book"], "contributor": ["ṣanʻatīʹzādah kirmānī"], "id": "http://www.loc.gov/item/2004433197/", "partof": ["african and middle eastern division", "catalog", "persian language rare materials"], "subject": ["mani", "manichaeism", "active 3rd century", "iran"], "index": 67, "group": ["amed/amedscd", "amed-scan-on-demand"], "location_country": ["iran"], "title": "Dāstān-i Mānī-i naqqāsh", "segments": [{"url": "https://www.loc.gov/resource/amedscd.2004433197/", "count": 126, "link": "https://www.loc.gov/collections/persian-language-rare-materials/?c=100&fa=segmentof:amedscd.2004433197/&fo=json&sb=shelf-id&st=gallery"}], "number_source_modified": ["2020-03-04t14:30:05"], "online_format": ["image"], "location": ["iran"], "resources": [{"files": 126, "search": "https://www.loc.gov/collections/persian-language-rare-materials/?c=100&fa=segmentof:amedscd.2004433197/&fo=json&sb=shelf-id&st=gallery", "url": "https://www.loc.gov/resource/amedscd.2004433197/", "image": "http://tile.loc.gov/image-services/iiif/service:amed:amedscd:2004433197:0003/full/pct:6.25/0/default.jpg", "segments": 126, "representative_index": 2}], "digitized": true, "description": ["Early imprint. In Persian."], "timestamp": "2020-03-30T14:10:27.553Z", "site": ["catalog"], "campaigns": [], "extract_timestamp": "2020-03-30T13:58:02.237Z", "date": "1926", "shelf_id": "BT1410 .S26 1926", "other_title": ["داستان مانى نقاش /"], "dates": ["1926-01-01T00:00:00Z"], "number_lccn": ["2004433197"], "language": ["persian"], "url": "https://www.loc.gov/item/2004433197/", "hassegments": true, "image_url": ["https://tile.loc.gov/image-services/iiif/service:amed:amedscd:2004433197:0003/full/pct:6.25/0/default.jpg", "https://tile.loc.gov/image-services/iiif/service:amed:amedscd:2004433197:0003/full/pct:6.25/0/default.jpg#h=264&w=190", "https://tile.loc.gov/image-services/iiif/service:amed:amedscd:2004433197:0003/full/pct:12.5/0/default.jpg#h=528&w=381", "https://tile.loc.gov/image-services/iiif/service:amed:amedscd:2004433197:0003/full/pct:25/0/default.jpg#h=1056&w=762", "https://tile.loc.gov/image-services/iiif/service:amed:amedscd:2004433197:0003/full/pct:50/0/default.jpg#h=2112&w=1524", "https://tile.loc.gov/image-services/iiif/service:amed:amedscd:2004433197:0003/full/pct:100/0/default.jpg#h=4224&w=3048"], "mime_type": ["image/tiff", "image/jpeg", "image/jp2"], "aka": ["http://www.loc.gov/item/2004433197/", "http://lccn.loc.gov/2004433197", "http://www.loc.gov/resource/amedscd.2004433197/", "https://hdl.loc.gov/loc.amed/amedscd.2004433197"]}