{"item": {"digital_id": ["https://hdl.loc.gov/loc.amed/amedpllc.00406537766"], "call_number": ["CE59 .H3325 1895"], "language": ["per"], "contributors": ["Hāshim ibn Nūr al-Dīn, author."], "title": "Kitāb-i Khulāṣah-ʼi Hāshimī dar dānistan-i ʻilm-i taqvīm", "notes": ["Lithographed."], "format": ["text"], "summary": ["On astronomy and Islamic calendar."], "subjects": ["Islamic calendar", "Islamic astronomy", "India"], "date": "1895", "created_published": ["Bambaʼī : Dat Prasād, 1313 [1895]"], "medium": ["214 pages, 2 unnumbered pages ; 21 cm"], "other_title": ["کتاب خلاصۀ هاشمى در دانستن علم تقويم /", "Khulāṣah-ʼi Hāshimī dar dānistan-i ʻilm-i taqvīm"]}, "access_restricted": false, "site": ["catalog"], "original_format": ["book"], "contributor": ["hāshim ibn nūr al-dīn"], "id": "http://www.loc.gov/item/2007432449/", "partof": ["african and middle eastern division", "catalog", "persian language rare materials"], "subject": ["islamic calendar", "india", "islamic astronomy"], "index": 68, "group": ["amed/amedpllc", "persian-language-rare-materials-lithographs"], "location_country": ["india"], "title": "Kitāb-i Khulāṣah-ʼi Hāshimī dar dānistan-i ʻilm-i taqvīm", "segments": [{"url": "https://www.loc.gov/resource/amedpllc.00406537766/", "count": 224, "link": "https://www.loc.gov/collections/persian-language-rare-materials/?c=100&fa=segmentof:amedpllc.00406537766/&fo=json&sb=shelf-id&st=gallery"}], "number_source_modified": ["2019-10-29t15:34:36"], "online_format": ["image"], "location": ["india"], "resources": [{"files": 224, "search": "https://www.loc.gov/collections/persian-language-rare-materials/?c=100&fa=segmentof:amedpllc.00406537766/&fo=json&sb=shelf-id&st=gallery", "url": "https://www.loc.gov/resource/amedpllc.00406537766/", "image": "http://tile.loc.gov/image-services/iiif/service:amed:amedpllc:00406537766:0005/full/pct:12.5/0/default.jpg", "segments": 224, "representative_index": 4}], "digitized": true, "description": ["On astronomy and Islamic calendar."], "timestamp": "2020-03-23T19:32:57.532Z", "number": ["2007432449", "2019-10-29t15:34:36"], "campaigns": [], "extract_timestamp": "2020-03-23T19:25:43.087Z", "date": "1895", "shelf_id": "CE59 .H3325 1895", "other_title": ["کتاب خلاصۀ هاشمى در دانستن علم تقويم /", "Khulāṣah-ʼi Hāshimī dar dānistan-i ʻilm-i taqvīm"], "dates": ["1895-01-01T00:00:00Z"], "number_lccn": ["2007432449"], "language": ["persian"], "url": "https://www.loc.gov/item/2007432449/", "hassegments": true, "image_url": ["https://tile.loc.gov/image-services/iiif/service:amed:amedpllc:00406537766:0005/full/pct:12.5/0/default.jpg", "https://tile.loc.gov/image-services/iiif/service:amed:amedpllc:00406537766:0005/full/pct:12.5/0/default.jpg#h=425&w=295", "https://tile.loc.gov/image-services/iiif/service:amed:amedpllc:00406537766:0005/full/pct:25/0/default.jpg#h=850&w=590", "https://tile.loc.gov/image-services/iiif/service:amed:amedpllc:00406537766:0005/full/pct:50/0/default.jpg#h=1701&w=1180", "https://tile.loc.gov/image-services/iiif/service:amed:amedpllc:00406537766:0005/full/pct:100/0/default.jpg#h=3402&w=2361"], "mime_type": ["image/jpeg", "image/jp2"], "aka": ["http://www.loc.gov/resource/amedpllc.00406537766/", "http://www.loc.gov/item/2007432449/", "http://lccn.loc.gov/2007432449", "https://hdl.loc.gov/loc.amed/amedpllc.00406537766"]}