{"iiif_manifest": "https://figgy.princeton.edu/concern/scanned_resources/20c5739f-9748-40ad-bcbd-76697e9e4584/manifest", "thumbnail": "https://iiif.princeton.edu/loris/figgy_prod/0c%2F17%2Fb2%2F0c17b2623c3446b08c0418d6dc215d82%2Fintermediate_file.jp2/full/!200,150/0/default.jpg", "rendering": "http://arks.princeton.edu/ark:/88435/p2677017n", "description": "Ms. codex.", "author": ["Muhammed bin Vaiz bin Velican Marʻaşî."], "contents": ["1. fol. 1b-4a: al-Tawḥīdīyah.", "2. fol. 4b-5a: al-Qalamīyah.", "3. fol. 5b-6a: ʻAndalīb.", "4. fol. 6b-11b: Sharḥ ʻAndalib.", "5. fol. 12b-17a: ʻAyn al-ḥayāh.", "6. fol. 18b-21b: Mukhtaṣar ʻAyn al-ḥayāh.", "7. fol. 22b-25b: Sharāb al-kawthar fī ʻilm al-maʻānī.", "8. fol. 26b-27a: Khulāṣat ḥāl wāliday al-Nabī.", "9. fol. 28b-32a: Nahr al-najāh.", "10. fol. 33b-35a: Ghāyat al-burhān.", "11. fol. 36b-46a: Salsabīl al-maʻānī.", "12. fol. 46b-47b: Zubdat al-munāẓarah.", "13. fol. 48b-49a: [Tafsīr al-Kawthar].", "14. fol. 49b-51b: Ḥāshiyat Sūrat al-Kawthar.", "15. fol. 52b-54a: Ṭarīq al-ṣawāb fī ʻilm al-ādāb.", "16. fol. 55b-60a: Risālah fī ʻilm al-maʻānī wa-al-bayān.", "17. fol. 60b-61a: Bayān kalām al-Imām al-Harawī.", "18. fol. 61b-62a: Salāmat al-qulūb fī bayān ithbāt al-maṭlūb.", "19. fol. 62b-65a: Sharḥ Salāmat al-qulūb fī bayān ithbāt al-maṭlūb.", "20. fol. 66b-68b: Insān al-ʻayn wa-ʻayn al-insān fī bayān uṣūl al-fiqh.", "21. fol. 69b-73b: ʻIṣmat al-adhhān fī ʻilm al-mīzān.", "22. fol. 74b: Risālah-i Zubdat al-dhahab. First page only."], "extent": ["74 leaves : paper ; 208 x 129 mm. bound to 208 x 135 mm."], "identifier": ["<a href='http://arks.princeton.edu/ark:/88435/p2677017n' alt='Identifier'>http://arks.princeton.edu/ark:/88435/p2677017n</a>"], "title": [{"@value": "Majmūʻat 22 risālah kulluhu", "@language": "ara"}], "dlme_title_ara_latn": "Majmūʻat 22 risālah kulluhu", "uniform_title": ["Selections"], "type": ["Commentaries"], "creator": ["Muhammed bin Vaiz bin Velican Marʻaşî."], "dlme_creator_ara_latn": "Muhammed bin Vaiz bin Velican Marʻaşî.", "date": ["1769-1776"], "language": ["Arabic"], "text_language": ["Arabic."], "publisher": ["[1769?-1776?]"], "subject": ["Qurʼan. Sūrat al-Kawthar—Commentaries—Early works to 1800"], "source_metadata_identifier": ["6217721"], "call_number": ["Islamic Manuscripts, New Series no. 1878", "Electronic Resource"], "member_of_collections": ["Princeton Digital Library of Islamic Manuscripts"]}