{"ObjectID": 30950, "ObjectNumber": "42.177", "SortNumber": "    42   177                                            ", "ObjectName": "seals (artifacts)", "CollectionID": 4, "Collection": "Ancient Art", "DateBeginYear": -1800, "DateEndYear": -1800, "DateText": "ca. 1800 BCE", "Title": "Cylinder Seal with Hieroglyphics", "Dimensions": "H: 3/4 × W: 1 1/4 in. (1.9 × 3.2 cm)", "Medium": "black steatite", "Style": null, "Culture": "Egyptian", "Inscriptions": null, "Classification": "Precious Stones & Gems", "Period": "Middle Kingdom", "Description": null, "CreditLine": "Acquired by Henry Walters, 1924", "ResourceURL": "http://art.thewalters.org/detail/30950", "Keywords": null, "Provenance": "Henry Walters, Baltimore, 1924, [mode of acquisition unknown]; Walters Art Museum, 1931, by bequest.", "Dynasty": "Twelfth Dynasty", "Reign": null, "OnView": 0, "PublicAccessDate": "2014-04-18T01:00:01.397", "Creator": "Egyptian", "PrimaryImage": {"Tiny": "http://static.thewalters.org/images/PL2_42.177_Fnt_BW.jpg?width=50", "Small": "http://static.thewalters.org/images/PL2_42.177_Fnt_BW.jpg?width=100", "Medium": "http://static.thewalters.org/images/PL2_42.177_Fnt_BW.jpg?width=150", "Large": "http://static.thewalters.org/images/PL2_42.177_Fnt_BW.jpg?width=250", "Raw": "http://static.thewalters.org/images/PL2_42.177_Fnt_BW.jpg"}, "GeoIDs": "", "ExhibIDs": "", "Images": "PL2_42.177_Fnt_BW.jpg", "DisplayLocation": "Not On View"}