{"ObjectID": 79739, "ObjectNumber": "W.658.97B", "SortNumber": "W        658   97B                                      ", "ObjectName": "illuminated manuscripts; folios (leaves); maps", "CollectionID": 3, "Collection": "Manuscripts", "DateBeginYear": 1658, "DateEndYear": 1800, "DateText": "late 11th century AH/AD 17th century-early 12th century AH/AD 18th century", "Title": "Map of the Bay of Kerme East of Cos Island", "Dimensions": "H: 13 3/8 x W: 9 7/16 in. (34 x 24 cm)", "Medium": "ink and pigments on laid European paper", "Style": null, "Culture": "Islamic", "Inscriptions": null, "Classification": "Manuscripts & Rare Books", "Period": "Ottoman", "Description": "This folio from Walters manuscript W.658 contains a map of the Bay of Kerme east of Cos (Stancho, Istanköy) Island.", "CreditLine": "Acquired by Henry Walters", "ResourceURL": "http://art.thewalters.org/detail/79739", "Keywords": "Art; Binding; Codex; Colophon; Headpiece; History; Illumination; Illustration; Islamic; Manuscript; Ornament; Painting; Turkish; Cartography; Geography", "Provenance": "Ahmad Afandi [date and mode of acquisition unknown] [see folio 4a]; Ali Afandi [date and mode of acquisiton unknown] [see folio 4a]; Sayyid Ali Qapudan [date and mode of acquisition unknown] [see folio 1a]; Sultan Mahmud Khan [date and mode of acquistion unknown] [waqf seal and followed by a bequest statement (now erased), and the seal of the inspector of wakfs, Mustafá Tahir, see folio 4a]; Henry Walters, Baltimore [date and mode of acquisition unknown]; Walters Art Museum, 1931, by bequest.", "Dynasty": null, "Reign": null, "OnView": 0, "PublicAccessDate": "2014-01-24T13:51:40.93", "Creator": "Piri Reis (Turkish, 1465-1555)", "PrimaryImage": {"Tiny": "http://static.thewalters.org/images/CPS_W.658.97b_Fp_DD_300.jpg?width=50", "Small": "http://static.thewalters.org/images/CPS_W.658.97b_Fp_DD_300.jpg?width=100", "Medium": "http://static.thewalters.org/images/CPS_W.658.97b_Fp_DD_300.jpg?width=150", "Large": "http://static.thewalters.org/images/CPS_W.658.97b_Fp_DD_300.jpg?width=250", "Raw": "http://static.thewalters.org/images/CPS_W.658.97b_Fp_DD_300.jpg"}, "GeoIDs": "1431914, 1501112, 1501790", "ExhibIDs": "", "Images": "CPS_W.658.97b_Fp_DD_300.jpg", "DisplayLocation": "Not on View"}