{"ObjectID": 15021, "ObjectNumber": "48.312", "SortNumber": "    48   312                                            ", "ObjectName": "figurines", "CollectionID": 4, "Collection": "Ancient Art", "DateBeginYear": -100, "DateEndYear": -1, "DateText": "1st century BC", "Title": "Male Head with Laurel Leaf", "Dimensions": "H: 5 5/8 in. (14.3 cm)", "Medium": "Egyptian faience", "Style": null, "Culture": "Egyptian", "Inscriptions": null, "Classification": "Ceramics", "Period": "Greco-Roman", "Description": "The combination of the laurel wreath and the lotus leaf over the forehead suggests that this man was likely a deified ruler.", "CreditLine": "Acquired by Henry Walters", "ResourceURL": "http://art.thewalters.org/detail/15021", "Keywords": null, "Provenance": "Giovanni Dattri, Cairo, [date and mode of acquisition unknown]; Lambros-Dattari Sale, Cairo, Paris, 1912, June 17-19, 1912, p. 355, no. 492, pl. 44; Henry Walters, Baltimore [date and mode of acquisition unknown]; Walters Art Museum, 1931, by bequest.", "Dynasty": "Ptolemaic Dynasty", "Reign": null, "OnView": 0, "PublicAccessDate": "2014-04-18T01:00:01.397", "Creator": "Egyptian", "PrimaryImage": {"Tiny": "http://static.thewalters.org/images/PL2_48.312_Fnt_BW_C40.jpg?width=50", "Small": "http://static.thewalters.org/images/PL2_48.312_Fnt_BW_C40.jpg?width=100", "Medium": "http://static.thewalters.org/images/PL2_48.312_Fnt_BW_C40.jpg?width=150", "Large": "http://static.thewalters.org/images/PL2_48.312_Fnt_BW_C40.jpg?width=250", "Raw": "http://static.thewalters.org/images/PL2_48.312_Fnt_BW_C40.jpg"}, "GeoIDs": "1543485", "ExhibIDs": "10, 358", "Images": "PL2_48.312_Fnt_BW_C40.jpg", "DisplayLocation": "Not On View"}