{"ObjectID": 83868, "ObjectNumber": "W.747.B", "SortNumber": "W        747B                                           ", "ObjectName": "illuminated manuscripts; folios (leaves)", "CollectionID": 3, "Collection": "Manuscripts", "DateBeginYear": 1550, "DateEndYear": 1600, "DateText": "mid 10th century AH/AD 16th century", "Title": "Mounted Figure Attacked by a Lion (Back)", "Dimensions": "H: 12 13/16 x W: 8 11/16 in. (32.5 x 22 cm)", "Medium": "ink and pigments on paper mounted on pasteboard", "Style": null, "Culture": "Islamic", "Inscriptions": null, "Classification": "Manuscripts & Rare Books", "Period": "Safavid", "Description": "This manuscript leaf, Walters W.747, is the back of an illustration of a mounted figures attacked by a lion.", "CreditLine": "Museum purchase, 1952", "ResourceURL": "http://art.thewalters.org/detail/83868", "Keywords": "Islamic; Persian; Safavid; Illustration; Miniature; Drawing; Iran", "Provenance": "Kelekian Estate, 1952, by bequest; Walters Art Museum, 1952, by purchase.", "Dynasty": "Safavid Dynasty", "Reign": null, "OnView": 0, "PublicAccessDate": "2014-01-24T13:51:40.93", "Creator": "Iranian", "PrimaryImage": {"Tiny": "http://static.thewalters.org/images/CPS_W.747.b_Fp_DD.jpg?width=50", "Small": "http://static.thewalters.org/images/CPS_W.747.b_Fp_DD.jpg?width=100", "Medium": "http://static.thewalters.org/images/CPS_W.747.b_Fp_DD.jpg?width=150", "Large": "http://static.thewalters.org/images/CPS_W.747.b_Fp_DD.jpg?width=250", "Raw": "http://static.thewalters.org/images/CPS_W.747.b_Fp_DD.jpg"}, "GeoIDs": "1507667", "ExhibIDs": "", "Images": "CPS_W.747.b_Fp_DD.jpg", "DisplayLocation": "Not on View"}