{"id": "https://cdm21044.contentdm.oclc.org/iiif/info/emirgan/906/manifest.json", "resource": {"@id": "https://cdm21044.contentdm.oclc.org/digital/iiif/emirgan/904/full/full/0/default.jpg", "@type": "dctypes:Image", "service": {"@context": "http://iiif.io/api/image/2/context.json", "@id": "https://cdm21044.contentdm.oclc.org/digital/iiif/emirgan/904", "width": 1007, "height": 1577, "tiles": [{"width": 1007, "scaleFactors": [1, 2, 4, 8, 16]}], "profile": "http://iiif.io/api/image/2/level1.json", "protocol": "http://iiif.io/api/image"}, "format": "image/jpeg", "width": 1007, "height": 1577}, "tür_(type)": "Fotoğraf", "envanter_numarası_(identifier)": "E-F 109", "başlık_(title)": "Portre", "dil_(language)": "Türkçe-Osmanlıca", "tarih_(date)": "1921", "boyutlar_(measurements)": "13,2 x 8,8 cm", "kayıtlar_(inscriptions/marks)": "Arka: Arapça \"1337\"; \"1337 senesi müdür Fadıl B muallim Tevfik\"", "açıklama_(description)": "1337 Rumi yılı, 1921 Miladi yılının karşılığıdır.", "ayrıca_bakınız_(see_also)": "E-F 110", "bulunduğu_yer_(current_repository)": "Sabancı Üniversitesi Sakıp Sabancı Müzesi (Emirgan, İstanbul, Türkiye)", "telif_hakkı_(copyright)": "© Sabancı Üniversitesi Sakıp Sabancı Müzesi. Tüm hakları saklıdır.", "repository": "digitalSSM", "source": "<span>From: <a href=\"http://www.digitalssm.org/digital/collection/emirgan/id/906\">Portre</a></span>", "context": "http://iiif.io/api/presentation/2/context.json"}