{"id": "https://cdm21044.contentdm.oclc.org/iiif/info/emirgan/867/manifest.json", "resource": {"@id": "https://cdm21044.contentdm.oclc.org/digital/iiif/emirgan/865/full/full/0/default.jpg", "@type": "dctypes:Image", "service": {"@context": "http://iiif.io/api/image/2/context.json", "@id": "https://cdm21044.contentdm.oclc.org/digital/iiif/emirgan/865", "width": 1657, "height": 1095, "tiles": [{"width": 1657, "scaleFactors": [1, 2, 4, 8, 16]}], "profile": "http://iiif.io/api/image/2/level1.json", "protocol": "http://iiif.io/api/image"}, "format": "image/jpeg", "width": 1657, "height": 1095}, "type": "Kartpostal", "identifier": "E-F 162", "title": "Emirgan", "language": "Fransızca", "measurements": "9 x 13,8 cm", "current repository": "Sabancı Üniversitesi Sakıp Sabancı Müzesi (Emirgan, İstanbul, Türkiye)", "copyright": "© Sabancı Üniversitesi Sakıp Sabancı Müzesi. Tüm hakları saklıdır.", "repository": "digitalSSM", "source": "<span>From: <a href=\"http://www.digitalssm.org/digital/collection/emirgan/id/867\">Emirgan</a></span>", "context": "http://iiif.io/api/presentation/2/context.json"}