{"manifest": "https://cdm21044.contentdm.oclc.org/iiif/info/emirgan/903/manifest.json", "id": "https://cdm21044.contentdm.oclc.org/iiif/info/emirgan/903/manifest.json", "resource": "https://cdm21044.contentdm.oclc.org/digital/iiif/emirgan/901/full/full/0/default.jpg", "profile": "http://iiif.io/api/image/2/level1.json", "iiif_format": "image/jpeg", "type": "Fotoğraf", "identifier": "E-F 140", "title": "Baltalimanı", "language": "Fransızca", "date": "1932", "measurements": "6,1 x 9,1 cm", "inscriptions-marks": "Arkada Fransızca yazılar ve 25 Eylül 1932 yazılı", "see-also": "E-F 130; E-F 152", "current-repository": "Sabancı Üniversitesi Sakıp Sabancı Müzesi (Emirgan, İstanbul, Türkiye)", "copyright": "© Sabancı Üniversitesi Sakıp Sabancı Müzesi. Tüm hakları saklıdır.", "repository": "digitalSSM", "source": "<span>From: <a href=\"http://www.digitalssm.org/digital/collection/emirgan/id/903\">Baltalimanı</a></span>", "context": "http://iiif.io/api/presentation/2/context.json"}