{"id": "https://cdm21044.contentdm.oclc.org/iiif/info/emirgan/744/manifest.json", "resource": {"@id": "https://cdm21044.contentdm.oclc.org/digital/iiif/emirgan/742/full/full/0/default.jpg", "@type": "dctypes:Image", "service": {"@context": "http://iiif.io/api/image/2/context.json", "@id": "https://cdm21044.contentdm.oclc.org/digital/iiif/emirgan/742", "width": 974, "height": 1490, "tiles": [{"width": 974, "scaleFactors": [1, 2, 4, 8, 16]}], "profile": "http://iiif.io/api/image/2/level1.json", "protocol": "http://iiif.io/api/image"}, "format": "image/jpeg", "width": 974, "height": 1490}, "tür_(type)": "Fotoğraf", "envanter_numarası_(identifier)": "E-F 099", "başlık_(title)": "Portre", "dil_(language)": "Türkçe-Osmanlıca", "tarih_(date)": "1914", "boyutlar_(measurements)": "12,3 x 8 cm", "transkripsiyon_(transcription)": "Ön: Tevfik Ağabeyime hâtıra fi 23 Mart sene [1]330. [imza]", "açıklama_(description)": "23 Mart 1330 Rumi takvim, 05 Nisan 1914 Miladi takvimin karşığıdır.", "ayrıca_bakınız_(see_also)": "E-F 105; E-F 106", "bulunduğu_yer_(current_repository)": "Sabancı Üniversitesi Sakıp Sabancı Müzesi (Emirgan, İstanbul, Türkiye)", "telif_hakkı_(copyright)": "© Sabancı Üniversitesi Sakıp Sabancı Müzesi. Tüm hakları saklıdır.", "repository": "digitalSSM", "source": "<span>From: <a href=\"http://www.digitalssm.org/digital/collection/emirgan/id/744\">Portre</a></span>", "context": "http://iiif.io/api/presentation/2/context.json"}