{"title": "Kermanshah\u2019s Stonemasons Zurkhaneh", "title_detail": {"type": "text/plain", "language": null, "base": "http://shahrefarang.com/en/feed/?paged=5", "value": "Kermanshah\u2019s Stonemasons Zurkhaneh"}, "links": [{"rel": "alternate", "type": "text/html", "href": "http://shahrefarang.com/en/kermanshahs-stonemasons-zurkhaneh/"}], "link": "http://shahrefarang.com/en/kermanshahs-stonemasons-zurkhaneh/", "comments": "http://shahrefarang.com/en/kermanshahs-stonemasons-zurkhaneh/#respond", "published": "Sat, 08 Sep 2012 19:03:31 +0000", "published_parsed": [2012, 9, 8, 19, 3, 31, 5, 252, 0], "authors": [{"name": "\u0634\u0647\u0631\u0641\u0631\u0646\u06af"}], "author": "\u0634\u0647\u0631\u0641\u0631\u0646\u06af", "author_detail": {"name": "\u0634\u0647\u0631\u0641\u0631\u0646\u06af"}, "tags": [{"term": "Architecture", "scheme": null, "label": null}, {"term": "Everyday Life", "scheme": null, "label": null}, {"term": "Kermanshah", "scheme": null, "label": null}, {"term": "Sport", "scheme": null, "label": null}, {"term": "Wrestling", "scheme": null, "label": null}], "id": "http://shahrefarang.com/kermanshahs-stonemasons-zurkhaneh/", "guidislink": false, "summary": "Stonemason Zurkhaneh (\u201cZurkhaneh\u201d=traditional Iranian wrestling center) is located near the end of Shah-Abbasi Karevansaray and the Goldsmith\u2019s bazaar in the city of Kermanshah. The locals believe that its history goes back to 400 years ago. Many legendary traditional wrestlers of Kermanshah come from this sport club.", "summary_detail": {"type": "text/html", "language": null, "base": "http://shahrefarang.com/en/feed/?paged=5", "value": "Stonemason Zurkhaneh (\u201cZurkhaneh\u201d=traditional Iranian wrestling center) is located near the end of Shah-Abbasi Karevansaray and the Goldsmith\u2019s bazaar in the city of Kermanshah. The locals believe that its history goes back to 400 years ago. Many legendary traditional wrestlers of Kermanshah come from this sport club."}, "wfw_commentrss": "http://shahrefarang.com/en/kermanshahs-stonemasons-zurkhaneh/feed/", "slash_comments": "0", "media_content": [{"url": "http://shahrefarang.s3.amazonaws.com/wp-content/uploads/2012/08/Zoorkhaneh-01.jpg", "type": "image/jpeg", "medium": "image", "width": "100%", "height": "auto"}], "content": [{"type": "text/plain", "language": null, "base": "http://shahrefarang.com/en/feed/?paged=5", "value": "Kermanshah\u2019s Stonemasons Zurkhaneh"}]}