{"title": "Contemporary Mosques & Shrines", "title_detail": {"type": "text/plain", "language": null, "base": "http://shahrefarang.com/en/feed/?paged=8", "value": "Contemporary Mosques & Shrines"}, "links": [{"rel": "alternate", "type": "text/html", "href": "http://shahrefarang.com/en/contemporary-mosques-shrines/"}], "link": "http://shahrefarang.com/en/contemporary-mosques-shrines/", "comments": "http://shahrefarang.com/en/contemporary-mosques-shrines/#respond", "published": "Thu, 12 Jan 2012 12:00:00 +0000", "published_parsed": [2012, 1, 12, 12, 0, 0, 3, 12, 0], "authors": [{"name": "\u0634\u0647\u0631\u0641\u0631\u0646\u06af"}], "author": "\u0634\u0647\u0631\u0641\u0631\u0646\u06af", "author_detail": {"name": "\u0634\u0647\u0631\u0641\u0631\u0646\u06af"}, "tags": [{"term": "Beliefs", "scheme": null, "label": null}, {"term": "Building", "scheme": null, "label": null}, {"term": "Mosques", "scheme": null, "label": null}, {"term": "Religion", "scheme": null, "label": null}, {"term": "Shia", "scheme": null, "label": null}, {"term": "Shiism", "scheme": null, "label": null}, {"term": "Worship", "scheme": null, "label": null}], "id": "http://shahrefarang.com/contemporary-mosques-shrines/", "guidislink": false, "summary": "Today's architecture and design of mosques in Iran is becoming simpler and less elaborate than before. Most of these new mosques look more like half-built structures and are vaguely reminiscent of the glorious mosques of the past. Green is the dominant colour used in the majority of these contemporary mosques.", "summary_detail": {"type": "text/html", "language": null, "base": "http://shahrefarang.com/en/feed/?paged=8", "value": "Today's architecture and design of mosques in Iran is becoming simpler and less elaborate than before. Most of these new mosques look more like half-built structures and are vaguely reminiscent of the glorious mosques of the past. Green is the dominant colour used in the majority of these contemporary mosques."}, "wfw_commentrss": "http://shahrefarang.com/en/contemporary-mosques-shrines/feed/", "slash_comments": "0", "media_content": [{"url": "http://shahrefarang.s3.amazonaws.com/wp-content/uploads/2011/12/masjed-04-665x449.jpg", "type": "image/jpeg", "medium": "image", "width": "100%", "height": "auto"}], "content": [{"type": "text/plain", "language": null, "base": "http://shahrefarang.com/en/feed/?paged=8", "value": "Contemporary Mosques (4)"}]}