<record xmlns="http://www.openarchives.org/OAI/2.0/" xmlns:xsi="http://www.w3.org/2001/XMLSchema-instance">
	<header>
		<identifier>81055/vdc_100074830028.0x000003_dlme</identifier>
	</header>
	<ar_metadata>
<mods xmlns="http://www.loc.gov/mods/v3" xmlns:xsi="http://www.w3.org/2001/XMLSchema-instance" xmlns:xlink="http://www.w3.org/1999/xlink"><identifier>81055/vdc_100074830028.0x000003_ar</identifier><location><shelfLocator>IOR/L/PS/10/850/1</shelfLocator><url>http://www.qdl.qa/%D8%A7%D9%84%D8%B9%D8%B1%D8%A8%D9%8A%D8%A9/archive/81055/vdc_100074830028.0x000003</url><url access="preview">https://images.qdl.qa/iiif/images/81055/vdc_100000000419.0x0002e8/IOR_L_PS_10_850_0034.jp2/full/!1000,1000/0/default.jpg</url><physicalLocation>&#1575;&#1604;&#1605;&#1603;&#1578;&#1576;&#1577; &#1575;&#1604;&#1576;&#1585;&#1610;&#1591;&#1575;&#1606;&#1610;&#1577;: &#1571;&#1608;&#1585;&#1575;&#1602; &#1582;&#1575;&#1589;&#1577; &#1608;&#1587;&#1580;&#1604;&#1575;&#1578; &#1605;&#1606; &#1605;&#1603;&#1578;&#1576; &#1575;&#1604;&#1607;&#1606;&#1583;</physicalLocation></location><recordInfo><recordIdentifer>IOR/L/PS/10/850/1</recordIdentifer></recordInfo><titleInfo><title>&#1605;&#1604;&#1601; &#1636;&#1638;&#1639;&#1635;\ &#1633;&#1641;&#1633;&#1641; &#1575;&#1604;&#1580;&#1586;&#1569; &#1633; "&#1575;&#1604;&#1582;&#1604;&#1610;&#1580; &#1575;&#1604;&#1601;&#1575;&#1585;&#1587;&#1610;:- &#1586;&#1610;&#1575;&#1585;&#1577; &#1606;&#1580;&#1604; &#1588;&#1610;&#1582; &#1575;&#1604;&#1576;&#1581;&#1585;&#1610;&#1606; + &#1605;&#1580;&#1605;&#1608;&#1593;&#1577; &#1573;&#1604;&#1609; &#1573;&#1606;&#1580;&#1604;&#1578;&#1585;&#1575;. &#1575;&#1604;&#1578;&#1585;&#1578;&#1610;&#1576;&#1575;&#1578; &#1575;&#1604;&#1593;&#1575;&#1605;&#1577; + &#1575;&#1604;&#1573;&#1580;&#1585;&#1575;&#1569;&#1575;&#1578;. &#1605;&#1602;&#1583;&#1575;&#1585; &#1575;&#1604;&#1578;&#1603;&#1575;&#1604;&#1610;&#1601;."</title></titleInfo><originInfo><dateIssued>1903/1928</dateIssued><dateCaptured>2018-03-08T22:26:10</dateCaptured></originInfo><language><languageTerm authority="iso639-2b">eng</languageTerm></language><physicalDescription><extent>&#1605;&#1575;&#1583;&#1577; &#1608;&#1575;&#1581;&#1583;&#1577; (&#1634;&#1637;&#1640; &#1608;&#1585;&#1602;&#1577;)</extent></physicalDescription><abstract>&#1610;&#1581;&#1578;&#1608;&#1610; &#1607;&#1584;&#1575; &#1575;&#1604;&#1580;&#1586;&#1569; &#1593;&#1604;&#1609; &#1605;&#1585;&#1575;&#1587;&#1604;&#1575;&#1578; &#1576;&#1582;&#1589;&#1608;&#1589; &#1586;&#1610;&#1575;&#1585;&#1577; &#1576;&#1593;&#1579;&#1577; (&#1608;&#1601;&#1583;) &#1578;&#1590;&#1605; &#1593;&#1576;&#1583; &#1575;&#1604;&#1604;&#1607; &#1576;&#1606; &#1593;&#1610;&#1587;&#1609; &#1570;&#1604; &#1582;&#1604;&#1610;&#1601;&#1577;&#1548; &#1606;&#1580;&#1604; &#1575;&#1604;&#1588;&#1610;&#1582; &#1593;&#1610;&#1587;&#1609; &#1588;&#1610;&#1582; &#1575;&#1604;&#1576;&#1581;&#1585;&#1610;&#1606;&#1548; &#1608;&#1605;&#1581;&#1605;&#1583; &#1606;&#1580;&#1604; &#1593;&#1576;&#1583; &#1575;&#1604;&#1604;&#1607; &#1608;&#1587;&#1603;&#1585;&#1578;&#1610;&#1585; &#1593;&#1576;&#1583; &#1575;&#1604;&#1604;&#1607; &#1575;&#1604;&#1582;&#1575;&#1589; &#1580;&#1575;&#1587;&#1605; &#1588;&#1593;&#1585;&#1575;&#1608;&#1610; &#1608;&#1582;&#1575;&#1583;&#1605; &#1588;&#1582;&#1589;&#1610;&#1548; &#1573;&#1604;&#1609; &#1575;&#1604;&#1605;&#1605;&#1604;&#1603;&#1577; &#1575;&#1604;&#1605;&#1578;&#1581;&#1583;&#1577; &#1608;&#1576;&#1575;&#1585;&#1610;&#1587; &#1601;&#1610; &#1587;&#1606;&#1577; &#1633;&#1641;&#1633;&#1641;.&#1603;&#1605;&#1575; &#1610;&#1578;&#1590;&#1605;&#1606; &#1605;&#1585;&#1575;&#1587;&#1604;&#1575;&#1578; &#1576;&#1582;&#1589;&#1608;&#1589; &#1578;&#1585;&#1578;&#1610;&#1576;&#1575;&#1578; &#1575;&#1604;&#1586;&#1610;&#1575;&#1585;&#1577;&#1548; &#1608;&#1604;&#1603;&#1606; &#1571;&#1594;&#1604;&#1576; &#1575;&#1604;&#1605;&#1585;&#1575;&#1587;&#1604;&#1575;&#1578; &#1578;&#1578;&#1593;&#1604;&#1602; &#1576;&#1575;&#1604;&#1573;&#1606;&#1601;&#1575;&#1602; &#1593;&#1604;&#1609; &#1575;&#1604;&#1586;&#1610;&#1575;&#1585;&#1577;&#1548; &#1576;&#1605;&#1575; &#1601;&#1610; &#1584;&#1604;&#1603;: &#1605;&#1587;&#1571;&#1604;&#1577; &#1605;&#1583;&#1609; &#1602;&#1576;&#1608;&#1604; &#1589;&#1606;&#1583;&#1608;&#1602; &#1575;&#1604;&#1590;&#1610;&#1575;&#1601;&#1577; &#1575;&#1604;&#1581;&#1603;&#1608;&#1605;&#1610; &#1575;&#1604;&#1605;&#1587;&#1572;&#1608;&#1604;&#1610;&#1577; &#1593;&#1606; &#1575;&#1604;&#1606;&#1601;&#1602;&#1575;&#1578; &#1575;&#1604;&#1605;&#1585;&#1578;&#1576;&#1591;&#1577; &#1576;&#1575;&#1604;&#1586;&#1610;&#1575;&#1585;&#1577;&#1548; &#1576;&#1605;&#1575; &#1601;&#1610; &#1584;&#1604;&#1603; &#1575;&#1604;&#1605;&#1576;&#1604;&#1594; &#1575;&#1604;&#1584;&#1610; &#1587;&#1610;&#1583;&#1601;&#1593; &#1604;&#1604;&#1605;&#1578;&#1585;&#1580;&#1605;&#1563; &#1608;&#1578;&#1593;&#1583;&#1610;&#1604; &#1578;&#1602;&#1585;&#1610;&#1585; &#1575;&#1604;&#1585;&#1575;&#1574;&#1583; &#1606;&#1608;&#1585;&#1605;&#1575;&#1606; &#1606;&#1575;&#1576;&#1610;&#1610;&#1585; &#1576;&#1585;&#1575;&#1610; (&#1575;&#1604;&#1605;&#1587;&#1572;&#1608;&#1604; &#1575;&#1604;&#1587;&#1610;&#1575;&#1587;&#1610; &#1575;&#1604;&#1605;&#1604;&#1581;&#1602; &#1576;&#1576;&#1593;&#1579;&#1577; &#1575;&#1604;&#1576;&#1581;&#1585;&#1610;&#1606;) &#1601;&#1610;&#1605;&#1575; &#1610;&#1578;&#1593;&#1604;&#1602; &#1576;&#1576;&#1593;&#1579;&#1577; &#1575;&#1604;&#1576;&#1581;&#1585;&#1610;&#1606;.&#1578;&#1578;&#1590;&#1605;&#1606; &#1575;&#1604;&#1571;&#1591;&#1585;&#1575;&#1601; &#1575;&#1604;&#1585;&#1574;&#1610;&#1587;&#1610;&#1577; &#1604;&#1604;&#1605;&#1585;&#1575;&#1587;&#1604;&#1575;&#1578; &#1603;&#1604;&#1575;&#1611; &#1605;&#1606;: &#1605;&#1603;&#1578;&#1576; &#1575;&#1604;&#1607;&#1606;&#1583;&#1563; &#1575;&#1604;&#1605;&#1601;&#1608;&#1617;&#1590; &#1575;&#1604;&#1605;&#1583;&#1606;&#1610; &#1601;&#1610; &#1576;&#1594;&#1583;&#1575;&#1583; ("&#1587;&#1610;&#1575;&#1587;&#1610;&#1548; &#1576;&#1594;&#1583;&#1575;&#1583;")&#1563; &#1608;&#1586;&#1575;&#1585;&#1577; &#1575;&#1604;&#1582;&#1575;&#1585;&#1580;&#1610;&#1577;&#1563; &#1575;&#1604;&#1582;&#1586;&#1610;&#1606;&#1577;&#1563; &#1589;&#1606;&#1583;&#1608;&#1602; &#1575;&#1604;&#1590;&#1610;&#1575;&#1601;&#1577; &#1575;&#1604;&#1581;&#1603;&#1608;&#1605;&#1610;&#1548; &#1605;&#1603;&#1578;&#1576; &#1575;&#1604;&#1571;&#1588;&#1594;&#1575;&#1604; &#1575;&#1604;&#1576;&#1585;&#1610;&#1591;&#1575;&#1606;&#1610;&#1563; &#1606;&#1608;&#1585;&#1605;&#1575;&#1606; &#1606;&#1575;&#1576;&#1610;&#1610;&#1585; &#1576;&#1585;&#1575;&#1610;&#1563; &#1575;&#1604;&#1581;&#1603;&#1608;&#1605;&#1577; &#1601;&#1610; &#1575;&#1604;&#1607;&#1606;&#1583;&#1548; &#1575;&#1604;&#1573;&#1583;&#1575;&#1585;&#1577; &#1575;&#1604;&#1587;&#1610;&#1575;&#1587;&#1610;&#1577; &#1608;&#1575;&#1604;&#1582;&#1575;&#1585;&#1580;&#1610;&#1577;&#1563; &#1587;&#1603;&#1585;&#1578;&#1610;&#1585; &#1575;&#1604;&#1573;&#1583;&#1575;&#1585;&#1577; &#1575;&#1604;&#1587;&#1610;&#1575;&#1587;&#1610;&#1577; &#1601;&#1610; &#1581;&#1603;&#1608;&#1605;&#1577; &#1576;&#1608;&#1605;&#1576;&#1575;&#1610;&#1563; &#1575;&#1604;&#1581;&#1580; &#1593;&#1576;&#1583; &#1575;&#1604;&#1605;&#1580;&#1610;&#1583; &#1576;&#1604;&#1588;&#1575;&#1607;&#1548; &#1605;&#1606; &#1603;&#1604;&#1610;&#1577; &#1575;&#1604;&#1583;&#1585;&#1575;&#1587;&#1575;&#1578; &#1575;&#1604;&#1588;&#1585;&#1602;&#1610;&#1577;&#1548; &#1605;&#1593;&#1607;&#1583; &#1604;&#1606;&#1583;&#1606; (&#1575;&#1604;&#1605;&#1578;&#1585;&#1580;&#1605; &#1604;&#1604;&#1576;&#1593;&#1579;&#1577; &#1605;&#1606; &#1575;&#1604;&#1576;&#1581;&#1585;&#1610;&#1606;)&#1563; &#1575;&#1604;&#1605;&#1581;&#1575;&#1587;&#1576; &#1575;&#1604;&#1593;&#1575;&#1605; &#1601;&#1610; &#1576;&#1608;&#1605;&#1576;&#1575;&#1610;&#1563; &#1608;&#1575;&#1604;&#1605;&#1581;&#1575;&#1587;&#1576; &#1575;&#1604;&#1593;&#1575;&#1605; (&#1575;&#1604;&#1605;&#1583;&#1606;&#1610;) &#1601;&#1610; &#1576;&#1594;&#1583;&#1575;&#1583;.</abstract><typeOfResource>text</typeOfResource><genre type="class">&#1605;&#1575;&#1583;&#1577; &#1571;&#1585;&#1588;&#1610;&#1601;&#1610;&#1577;</genre><name type="corporate"><namePart>&#1575;&#1604;&#1605;&#1601;&#1608;&#1617;&#1614;&#1590; &#1575;&#1604;&#1605;&#1583;&#1606;&#1610;</namePart><role><roleTerm type="text">correspondent</roleTerm></role></name><name type="corporate"><namePart>&#1608;&#1586;&#1575;&#1585;&#1577; &#1575;&#1604;&#1582;&#1575;&#1585;&#1580;&#1610;&#1577;</namePart><role><roleTerm type="text">correspondent</roleTerm></role></name><name type="corporate"><namePart>&#1582;&#1586;&#1575;&#1606;&#1577; &#1575;&#1604;&#1581;&#1603;&#1608;&#1605;&#1577; &#1575;&#1604;&#1576;&#1585;&#1610;&#1591;&#1575;&#1606;&#1610;&#1577;</namePart><role><roleTerm type="text">correspondent</roleTerm></role></name><name type="corporate"><namePart>&#1589;&#1606;&#1583;&#1608;&#1602; &#1575;&#1604;&#1590;&#1610;&#1575;&#1601;&#1577; &#1575;&#1604;&#1581;&#1603;&#1608;&#1605;&#1610;</namePart><role><roleTerm type="text">correspondent</roleTerm></role></name><name type="corporate"><namePart>&#1575;&#1604;&#1581;&#1603;&#1608;&#1605;&#1577; &#1601;&#1610; &#1575;&#1604;&#1607;&#1606;&#1583;&#1548; &#1575;&#1604;&#1573;&#1583;&#1575;&#1585;&#1577; &#1575;&#1604;&#1587;&#1610;&#1575;&#1587;&#1610;&#1577; &#1608;&#1575;&#1604;&#1582;&#1575;&#1585;&#1580;&#1610;&#1577;</namePart><role><roleTerm type="text">correspondent</roleTerm></role></name><subject><topic>&#1575;&#1604;&#1573;&#1606;&#1601;&#1575;&#1602; &#1575;&#1604;&#1581;&#1603;&#1608;&#1605;&#1610;</topic></subject><subject><topic>&#1575;&#1604;&#1573;&#1606;&#1601;&#1575;&#1602;</topic></subject><accessCondition type="Use and reproduction" xlink:href="http://www.qdl.qa/%D8%A7%D9%84%D8%B9%D8%B1%D8%A8%D9%8A%D8%A9/archive/81055/vdc_100074830028.0x000003#share">&#1575;&#1604;&#1605;&#1615;&#1604;&#1603;&#1610;&#1577; &#1575;&#1604;&#1593;&#1575;&#1605;&#1577;</accessCondition><accessCondition type="Use and reproduction" xlink:href="http://www.qdl.qa/%D8%A7%D9%84%D8%B9%D8%B1%D8%A8%D9%8A%D8%A9/archive/81055/vdc_100074830028.0x000003#share">&#1585;&#1582;&#1589;&#1577; &#1575;&#1604;&#1605;&#1588;&#1575;&#1593; &#1575;&#1604;&#1573;&#1576;&#1583;&#1575;&#1593;&#1610; &#1604;&#1571;&#1594;&#1585;&#1575;&#1590; &#1594;&#1610;&#1585; &#1578;&#1580;&#1575;&#1585;&#1610;&#1577;</accessCondition><accessCondition type="Use and reproduction" xlink:href="http://www.qdl.qa/%D8%A7%D9%84%D8%B9%D8%B1%D8%A8%D9%8A%D8%A9/archive/81055/vdc_100074830028.0x000003#share">&#1594;&#1610;&#1585; &#1605;&#1593;&#1585;&#1608;&#1601;</accessCondition><accessCondition type="Use and reproduction" xlink:href="http://www.qdl.qa/%D8%A7%D9%84%D8%B9%D8%B1%D8%A8%D9%8A%D8%A9/archive/81055/vdc_100074830028.0x000003#share">&#1585;&#1582;&#1589;&#1577; &#1581;&#1603;&#1608;&#1605;&#1577; &#1605;&#1601;&#1578;&#1608;&#1581;&#1577;</accessCondition><accessCondition type="Use and reproduction" xlink:href="http://www.qdl.qa/%D8%A7%D9%84%D8%B9%D8%B1%D8%A8%D9%8A%D8%A9/archive/81055/vdc_100074830028.0x000003#share">&#1581;&#1602;&#1608;&#1602; &#1575;&#1604;&#1606;&#1588;&#1585; &#1571;&#1608; &#1602;&#1610;&#1608;&#1583; &#1581;&#1605;&#1575;&#1610;&#1577; &#1575;&#1604;&#1576;&#1610;&#1575;&#1606;&#1575;&#1578;</accessCondition></mods>	</ar_metadata>
	<en_metadata>
<mods xmlns="http://www.loc.gov/mods/v3" xmlns:xsi="http://www.w3.org/2001/XMLSchema-instance" xmlns:xlink="http://www.w3.org/1999/xlink"><identifier>81055/vdc_100074830028.0x000003_en</identifier><location><shelfLocator>IOR/L/PS/10/850/1</shelfLocator><url>http://www.qdl.qa/en/archive/81055/vdc_100074830028.0x000003</url><url access="preview">https://images.qdl.qa/iiif/images/81055/vdc_100000000419.0x0002e8/IOR_L_PS_10_850_0034.jp2/full/!1000,1000/0/default.jpg</url><physicalLocation>British Library: India Office Records and Private Papers</physicalLocation></location><recordInfo><recordIdentifer>IOR/L/PS/10/850/1</recordIdentifer></recordInfo><titleInfo><title>File 4673/1919 Pt 1 &#8216;Persian Gulf:- Visit to England of the son of the Sheikh of Bahrein + party. General arrangements + proceedings. Incidence of cost.&#8217;</title></titleInfo><originInfo><dateIssued>1903/1928</dateIssued><dateCaptured>2018-03-08T22:26:10</dateCaptured></originInfo><language><languageTerm authority="iso639-2b">eng</languageTerm></language><physicalDescription><extent>1 item (258 folios)</extent></physicalDescription><abstract>This part contains correspondence regarding the visit of a Mission (deputation) consisting of &#8216;Abdullah bin &#8216;&#298;s&#225; &#256;l Khal&#299;fah, son of Shaikh Isa of Bahrein [Bahrain], Abdullah&#8217;s son Muhammad, Abdullah&#8217;s Private Secretary Jasim Cheravi, and a personal servant, to the United Kingdom and Paris in 1919.It includes correspondence regarding arrangements for the visit, but most of the correspondence relates to expenditure on the visit, including: the question as to how far the Government Hospitality Fund accepts responsibility for the expenses connected with the visit, including the payment of an interpreter; and the adjustment of the account of Major Norman Napier Bray (Political Officer attached to the Bahrein Mission) in connection with the Bahrein Mission.The main correspondents include: the India Office; the Civil Commissioner, Baghdad (&#8216;Political, Baghdad&#8217;); the Foreign Office; the Treasury; the Government Hospitality Fund, HM Office of Works; Norman Napier Bray; the Government of India Foreign and Political Department; the Secretary to the Government of Bombay Political Department; Haji Abdul Majid Belshah, of the School of Oriental Studies, London Institution (Interpreter to the Mission from Bahrein); the Accountant General, Bombay; and the Accountant General, (Civil) Baghdad.</abstract><typeOfResource>text</typeOfResource><genre type="class">Archival item</genre><name type="corporate"><namePart>Civil Commissioner, Mesopotamia</namePart><role><roleTerm type="text">correspondent</roleTerm></role></name><name type="corporate"><namePart>Foreign Office</namePart><role><roleTerm type="text">correspondent</roleTerm></role></name><name type="corporate"><namePart>HM Treasury</namePart><role><roleTerm type="text">correspondent</roleTerm></role></name><name type="corporate"><namePart>Government Hospitality Fund</namePart><role><roleTerm type="text">correspondent</roleTerm></role></name><name type="corporate"><namePart>Government of India, Foreign and Political Department</namePart><role><roleTerm type="text">correspondent</roleTerm></role></name><subject><topic>Government spending</topic></subject><subject><topic>Expenditure</topic></subject><accessCondition type="Use and reproduction" xlink:href="http://www.qdl.qa/en/archive/81055/vdc_100074830028.0x000003#share">Public Domain</accessCondition><accessCondition type="Use and reproduction" xlink:href="http://www.qdl.qa/en/archive/81055/vdc_100074830028.0x000003#share">Creative Commons Non-Commercial Licence</accessCondition><accessCondition type="Use and reproduction" xlink:href="http://www.qdl.qa/en/archive/81055/vdc_100074830028.0x000003#share">Unknown</accessCondition><accessCondition type="Use and reproduction" xlink:href="http://www.qdl.qa/en/archive/81055/vdc_100074830028.0x000003#share">Open Government Licence</accessCondition><accessCondition type="Use and reproduction" xlink:href="http://www.qdl.qa/en/archive/81055/vdc_100074830028.0x000003#share">Copyright or data protection restrictions</accessCondition></mods>	</en_metadata>
</record>
