<record xmlns="http://www.openarchives.org/OAI/2.0/" xmlns:xsi="http://www.w3.org/2001/XMLSchema-instance">
	<header>
		<identifier>81055/vdc_100000000833.0x00025d_dlme</identifier>
	</header>
	<ar_metadata>
<mods xmlns="http://www.loc.gov/mods/v3" xmlns:xsi="http://www.w3.org/2001/XMLSchema-instance" xmlns:xlink="http://www.w3.org/1999/xlink"><identifier>81055/vdc_100000000833.0x00025d_ar</identifier><location><shelfLocator>IOR/L/PS/18/B235</shelfLocator><url>http://www.qdl.qa/%D8%A7%D9%84%D8%B9%D8%B1%D8%A8%D9%8A%D8%A9/archive/81055/vdc_100000000833.0x00025d</url><url access="preview">https://images.qdl.qa/iiif/images/81055/vdc_100000000833.0x00025d/IOR_L_PS_18_B235_0001.jp2/full/!1000,1000/0/default.jpg</url><physicalLocation>&#1575;&#1604;&#1605;&#1603;&#1578;&#1576;&#1577; &#1575;&#1604;&#1576;&#1585;&#1610;&#1591;&#1575;&#1606;&#1610;&#1577;: &#1571;&#1608;&#1585;&#1575;&#1602; &#1582;&#1575;&#1589;&#1577; &#1608;&#1587;&#1580;&#1604;&#1575;&#1578; &#1605;&#1606; &#1605;&#1603;&#1578;&#1576; &#1575;&#1604;&#1607;&#1606;&#1583;</physicalLocation></location><recordInfo><recordIdentifer>IOR/L/PS/18/B235</recordIdentifer></recordInfo><titleInfo><title>"&#1575;&#1604;&#1579;&#1608;&#1585;&#1577; &#1575;&#1604;&#1593;&#1585;&#1576;&#1610;&#1577;. &#1608;&#1580;&#1607;&#1577; &#1606;&#1592;&#1585; &#1607;&#1606;&#1583;&#1610; &#1605;&#1587;&#1604;&#1605;."</title></titleInfo><originInfo><dateIssued>1916/1916</dateIssued><dateCaptured>2014-10-15T00:23:24</dateCaptured></originInfo><language><languageTerm authority="iso639-2b">eng</languageTerm></language><physicalDescription><extent>&#1608;&#1585;&#1602;&#1578;&#1575;&#1606;</extent><extent>&#1578;&#1585;&#1602;&#1610;&#1605; &#1575;&#1604;&#1571;&#1608;&#1585;&#1575;&#1602;: &#1610;&#1576;&#1583;&#1571; &#1578;&#1587;&#1604;&#1587;&#1604; &#1578;&#1585;&#1602;&#1610;&#1605; &#1575;&#1604;&#1571;&#1608;&#1585;&#1575;&#1602; &#1576;&#1575;&#1604;&#1608;&#1585;&#1602;&#1577; &#1575;&#1604;&#1571;&#1608;&#1604;&#1609; &#1608;&#1610;&#1606;&#1578;&#1607;&#1610; &#1576;&#1575;&#1604;&#1608;&#1585;&#1602;&#1577; &#1575;&#1604;&#1571;&#1582;&#1610;&#1585;&#1577;&#1563; &#1608;&#1607;&#1584;&#1607; &#1575;&#1604;&#1571;&#1585;&#1602;&#1575;&#1605; &#1605;&#1603;&#1578;&#1608;&#1576;&#1577; &#1576;&#1575;&#1604;&#1602;&#1604;&#1605; &#1575;&#1604;&#1585;&#1589;&#1575;&#1589; &#1608;&#1605;&#1581;&#1575;&#1591;&#1577; &#1576;&#1583;&#1575;&#1574;&#1585;&#1577; &#1601;&#1610; &#1571;&#1593;&#1604;&#1609; &#1610;&#1605;&#1610;&#1606; &#1589;&#1601;&#1581;&#1577; &#1575;&#1604;&#1608;&#1580;&#1607; &#1605;&#1606; &#1603;&#1604; &#1608;&#1585;&#1602;&#1577;.</extent></physicalDescription><abstract>&#1605;&#1584;&#1603;&#1585;&#1577; &#1587;&#1585;&#1610;&#1577; &#1578;&#1581;&#1578;&#1608;&#1610; &#1593;&#1604;&#1609; &#1605;&#1602;&#1578;&#1591;&#1601; &#1605;&#1606; &#1585;&#1587;&#1575;&#1604;&#1577;&#1548; &#1578;&#1604;&#1602;&#1575;&#1607;&#1575; &#1573;&#1583;&#1608;&#1575;&#1585;&#1583; &#1573;&#1610;&#1585;&#1606;&#1587;&#1578; &#1604;&#1608;&#1606;&#1580;&#1548; &#1605;&#1581;&#1585;&#1585; &#1587;&#1575;&#1576;&#1602; &#1604;&#1583;&#1609; &#1589;&#1581;&#1610;&#1601;&#1577;
                           &#1573;&#1606;&#1583;&#1610;&#1575;&#1606; &#1583;&#1610;&#1604;&#1610; &#1578;&#1610;&#1604;&#1610;&#1580;&#1585;&#1575;&#1601;&#1548; &#1608;&#1603;&#1578;&#1576;&#1607;&#1575; &#1607;&#1606;&#1583;&#1610; &#1605;&#1587;&#1604;&#1605; &#1594;&#1610;&#1585; &#1605;&#1593;&#1585;&#1608;&#1601; &#1575;&#1604;&#1575;&#1587;&#1605;. &#1606;&#1587;&#1582;&#1577; &#1605;&#1606; &#1585;&#1587;&#1575;&#1604;&#1577; &#1571;&#1582;&#1585;&#1609; &#1603;&#1578;&#1576;&#1607;&#1575; &#1604;&#1608;&#1606;&#1580; &#1576;&#1578;&#1575;&#1585;&#1610;&#1582; &#1639; &#1610;&#1608;&#1604;&#1610;&#1608; &#1633;&#1641;&#1633;&#1638; &#1578;&#1587;&#1576;&#1602; &#1575;&#1604;&#1585;&#1587;&#1575;&#1604;&#1577; &#1575;&#1604;&#1571;&#1587;&#1575;&#1587;&#1610;&#1577;&#1548; &#1610;&#1587;&#1578;&#1593;&#1585;&#1590; &#1601;&#1610;&#1607;&#1575; &#1604;&#1608;&#1606;&#1580; &#1608;&#1580;&#1607;&#1577; &#1606;&#1592;&#1585; &#1575;&#1604;&#1605;&#1587;&#1604;&#1605; &#1593;&#1604;&#1609; &#1571;&#1606;&#1607;&#1575; "&#1605;&#1572;&#1610;&#1583;&#1577; &#1604;&#1578;&#1585;&#1603;&#1610;&#1575; &#1575;&#1604;&#1601;&#1578;&#1575;&#1577;" &#1608;&#1578;&#1605;&#1579;&#1604; "&#1593;&#1585;&#1590;&#1611;&#1575; &#1605;&#1606;&#1589;&#1601;&#1611;&#1575;" &#1604;&#1608;&#1580;&#1607;&#1575;&#1578; &#1606;&#1592;&#1585; &#1575;&#1604;&#1607;&#1606;&#1608;&#1583; &#1575;&#1604;&#1605;&#1587;&#1604;&#1605;&#1610;&#1606;. &#1578;&#1578;&#1593;&#1604;&#1617;&#1602; &#1575;&#1604;&#1585;&#1587;&#1575;&#1604;&#1577; &#1575;&#1604;&#1608;&#1575;&#1585;&#1583;&#1577; &#1605;&#1606; &#1575;&#1604;&#1607;&#1606;&#1583;&#1610; &#1575;&#1604;&#1605;&#1587;&#1604;&#1605; &#1576;&#1587;&#1610;&#1575;&#1587;&#1577; &#1576;&#1585;&#1610;&#1591;&#1575;&#1606;&#1610;&#1575; &#1576;&#1593;&#1583;&#1605; &#1575;&#1604;&#1578;&#1583;&#1582;&#1604; &#1601;&#1610; &#1575;&#1604;&#1571;&#1605;&#1575;&#1603;&#1606; &#1575;&#1604;&#1573;&#1587;&#1604;&#1575;&#1605;&#1610;&#1577; &#1575;&#1604;&#1605;&#1602;&#1583;&#1617;&#1587;&#1577;&#1548; &#1608;&#1575;&#1604;&#1579;&#1608;&#1585;&#1577; &#1575;&#1604;&#1593;&#1585;&#1576;&#1610;&#1577;&#1548; &#1608;&#1602;&#1589;&#1601; &#1573;&#1581;&#1583;&#1609; &#1587;&#1601;&#1606; &#1575;&#1604;&#1571;&#1587;&#1591;&#1608;&#1604; &#1575;&#1604;&#1573;&#1606;&#1580;&#1604;&#1610;&#1586;&#1610; &#1604;&#1580;&#1583;&#1577; &#1601;&#1610; &#1633;&#1632; &#1610;&#1608;&#1606;&#1610;&#1608; &#1633;&#1641;&#1633;&#1638;. &#1610;&#1581;&#1584;&#1617;&#1585; &#1575;&#1604;&#1605;&#1585;&#1587;&#1604; &#1605;&#1606; &#1571;&#1606; &#1575;&#1604;&#1579;&#1608;&#1585;&#1577; &#1575;&#1604;&#1593;&#1585;&#1576;&#1610;&#1577; &#1602;&#1583; &#1578;&#1605;&#1606;&#1581; &#1575;&#1604;&#1571;&#1578;&#1585;&#1575;&#1603; &#1571;&#1601;&#1590;&#1604;&#1610;&#1577; &#1605;&#1593;&#1606;&#1608;&#1610;&#1577; &#1608;&#1593;&#1587;&#1603;&#1585;&#1610;&#1577;&#1548; &#1608;&#1610;&#1581;&#1584;&#1617;&#1585; &#1605;&#1606; &#1575;&#1604;&#1578;&#1583;&#1582;&#1604; &#1575;&#1604;&#1573;&#1606;&#1580;&#1604;&#1610;&#1586;&#1610; &#1608;&#1575;&#1604;&#1578;&#1581;&#1575;&#1604;&#1601; &#1601;&#1610; &#1575;&#1604;&#1581;&#1580;&#1575;&#1586;.</abstract><typeOfResource>text</typeOfResource><genre type="class">&#1605;&#1604;&#1601; &#1571;&#1585;&#1588;&#1610;&#1601;&#1610;</genre><subject><geographic>&#1575;&#1604;&#1581;&#1580;&#1575;&#1586;</geographic></subject><subject><geographic>&#1580;&#1583;&#1577;</geographic></subject><subject><topic>&#1575;&#1604;&#1581;&#1585;&#1576; &#1575;&#1604;&#1593;&#1575;&#1604;&#1605;&#1610;&#1577; &#1575;&#1604;&#1571;&#1608;&#1604;&#1609; (&#1633;&#1641;&#1633;&#1636;-&#1633;&#1641;&#1633;&#1640;)</topic></subject><subject><topic>&#1575;&#1604;&#1579;&#1608;&#1585;&#1577; &#1575;&#1604;&#1593;&#1585;&#1576;&#1610;&#1577; (&#1633;&#1641;&#1633;&#1638;-&#1633;&#1641;&#1633;&#1640;)</topic></subject><accessCondition type="Use and reproduction" xlink:href="http://www.qdl.qa/%D8%A7%D9%84%D8%B9%D8%B1%D8%A8%D9%8A%D8%A9/archive/81055/vdc_100000000833.0x00025d#share">&#1594;&#1610;&#1585; &#1605;&#1593;&#1585;&#1608;&#1601;</accessCondition><accessCondition type="Use and reproduction" xlink:href="http://www.qdl.qa/%D8%A7%D9%84%D8%B9%D8%B1%D8%A8%D9%8A%D8%A9/archive/81055/vdc_100000000833.0x00025d#share">&#1585;&#1582;&#1589;&#1577; &#1581;&#1603;&#1608;&#1605;&#1577; &#1605;&#1601;&#1578;&#1608;&#1581;&#1577;</accessCondition></mods>	</ar_metadata>
	<en_metadata>
<mods xmlns="http://www.loc.gov/mods/v3" xmlns:xsi="http://www.w3.org/2001/XMLSchema-instance" xmlns:xlink="http://www.w3.org/1999/xlink"><identifier>81055/vdc_100000000833.0x00025d_en</identifier><location><shelfLocator>IOR/L/PS/18/B235</shelfLocator><url>http://www.qdl.qa/en/archive/81055/vdc_100000000833.0x00025d</url><url access="preview">https://images.qdl.qa/iiif/images/81055/vdc_100000000833.0x00025d/IOR_L_PS_18_B235_0001.jp2/full/!1000,1000/0/default.jpg</url><physicalLocation>British Library: India Office Records and Private Papers</physicalLocation></location><recordInfo><recordIdentifer>IOR/L/PS/18/B235</recordIdentifer></recordInfo><titleInfo><title>&#8216;The Arab Revolt. Views of an Indian Moslem [Muslim].&#8217;</title></titleInfo><originInfo><dateIssued>1916/1916</dateIssued><dateCaptured>2014-10-15T00:23:24</dateCaptured></originInfo><language><languageTerm authority="iso639-2b">eng</languageTerm></language><physicalDescription><extent>2 folios</extent><extent>Foliation: The foliation sequence commences at the first folio and terminates at the last folio; these numbers are written in pencil, are circled, and are located in the top right corner of the recto side of each folio.</extent></physicalDescription><abstract>A secret memorandum containing an extract of a letter, received by Edward Ernest Long, former editor of the
                           Indian Daily Telegraph, and written by an unnamed Indian Muslim. A copy of another letter, written by Long, dated 7 July 1916, precedes the main letter, in which Long describes the views of the Muslim as being &#8216;pro-Young Turk&#8217;, and a &#8216;fair exposition&#8217; of the views of Indian Muslims. The letter from the Indian Muslim concerns Britain&#8217;s policy of non-intervention in the Holy Places of Islam, the Arab Revolt, and the bombardment of Jeddah in the Hedjaz [Hejaz/al-&#7716;ij&#257;z] by a British naval vessel on 10 June 1916. The correspondent warns that the Arab revolt may hand the Turks a moral and military advantage, and cautions against British and Allied involvement in the Hejaz.</abstract><typeOfResource>text</typeOfResource><genre type="class">Archival file</genre><subject><geographic>Hejaz</geographic></subject><subject><geographic>Jeddah</geographic></subject><subject><topic>First World War (1914-1918)</topic></subject><subject><topic>Arab Revolt (1916-1918)</topic></subject><accessCondition type="Use and reproduction" xlink:href="http://www.qdl.qa/en/archive/81055/vdc_100000000833.0x00025d#share">Unknown</accessCondition><accessCondition type="Use and reproduction" xlink:href="http://www.qdl.qa/en/archive/81055/vdc_100000000833.0x00025d#share">Open Government Licence</accessCondition></mods>	</en_metadata>
</record>
