<srw:record xmlns:srw="http://www.loc.gov/zing/srw/" xmlns:ns7="http://gallica.bnf.fr/namespaces/gallica/" xmlns:oai_dc="http://www.openarchives.org/OAI/2.0/oai_dc/" xmlns:onix_dc="http://bibnum.bnf.fr/NS/onix_dc/" xmlns:onix="http://www.editeur.org/onix/2.1/reference/" xmlns:dc="http://purl.org/dc/elements/1.1/">
            <srw:recordSchema>http://www.openarchives.org/OAI/2.0/OAIdc.xsd</srw:recordSchema>
            <srw:recordPacking>xml</srw:recordPacking>
            <srw:recordData>
                <oai_dc:dc>
                    <dc:contributor>Directeur - Müdir-i Mesul: E. Kemal, Rédacteur en chef - Ser muharriri: Ekrem Reşid.</dc:contributor>
                    <dc:date>1927-10-12</dc:date>
                    <dc:description>Haftada bir gün neşr olunur.</dc:description>
                    <dc:format>21-28 cm</dc:format>
                    <dc:identifier>PFFLM927</dc:identifier>
                    <dc:identifier>http://www.archives.saltresearch.org/R/?func=dbin-jump-full&amp;object_id=663031</dc:identifier>
                    <dc:language>French</dc:language>
                    <dc:publisher>İkdam Matbaası</dc:publisher>
                    <dc:relation>vignette : http://www.archives.saltresearch.org/webclient/DeliveryManager?pid=692088</dc:relation>
                    <dc:rights>Open Access</dc:rights>
                    <dc:title>Le Film - Film Mecmuası. Umûm-i sinema ve sanat aleminden bahseder müstakil ve bî taraf sinema mecmuasıdır.</dc:title>
                    <dc:type>Review</dc:type>
                </oai_dc:dc>
            </srw:recordData>
            <srw:recordIdentifier>ark</srw:recordIdentifier>
            <srw:recordPosition>3</srw:recordPosition>
            <srw:extraRecordData>
                <epubFile/>
                <infoSupModifiable/>
                <link>http://www.archives.saltresearch.org/R/?func=dbin-jump-full&amp;object_id=663031 </link>
                <nqamoyen>0.0</nqamoyen>
                <thumbnail> http://www.archives.saltresearch.org/webclient/DeliveryManager?pid=692088 </thumbnail>
                <typedoc>periodiques</typedoc>
            </srw:extraRecordData>
        </srw:record>
        
