<oai_dc:dc xmlns:oai_dc="http://www.openarchives.org/OAI/2.0/oai_dc/" xmlns:doc="http://www.lyncode.com/xoai" xmlns:xsi="http://www.w3.org/2001/XMLSchema-instance" xmlns:dc="http://purl.org/dc/elements/1.1/" xsi:schemaLocation="http://www.openarchives.org/OAI/2.0/oai_dc/ http://www.openarchives.org/OAI/2.0/oai_dc.xsd">
  <identifier>4771</identifier>
  <datestamp>2019-02-27T12:35:12Z</datestamp>
  <dc:title>Interview with Maryam Fatḥallāh al-Sa‘dī and Nimir ʻAlī ʻĪsá</dc:title>
  <dc:title>مقابلة مع مريم فتح الله السعدي ونمر علي عيسى</dc:title>
  <dc:interviewer>Balʻūs, Rāʼidah</dc:interviewer>
  <dc:interviewerAR>بلعوس، رائدة</dc:interviewerAR>
  <dc:interviewee>al-Sa‘dī, Maryam Fatḥallāh</dc:interviewee>
  <dc:interviewee>ʻĪsá, Nimir ʻAlī</dc:interviewee>
  <dc:intervieweeAR>السعدي، مريم فتح الله</dc:intervieweeAR>
  <dc:intervieweeAR>عيسى، نمر علي</dc:intervieweeAR>
  <dc:contributor />
  <dc:contributor>السعدي، مريم فتح الله</dc:contributor>
  <dc:contributor>عيسى، نمر علي</dc:contributor>
  <dc:contributor>بلعوس، رائدة</dc:contributor>
  <dc:subject>Folk songs, Arabic--Palestine--History and criticism</dc:subject>
  <dc:subjectAR>الأغاني الشعبية العربية--فلسطين--تاريخ ونقد</dc:subjectAR>
  <dc:subject>Marriage customs and rites--Palestine--20th century</dc:subject>
  <dc:subjectAR>عادات وطقوس الزواج--فلسطين--القرن العشرون</dc:subjectAR>
  <dc:subject>Weddings--Songs and music</dc:subject>
  <dc:subjectAR>الأعراس--الأغاني والموسيقى</dc:subjectAR>
  <dc:subject>Short stories, Arabic--Palestine</dc:subject>
  <dc:subjectAR>القصص القصيرة العربية--فلسطين</dc:subjectAR>
  <dc:otherSubject>Agriculture; Arab countries; Bedouin women; Dabkah; Dalʻūnā; Druzes; Girls; God; Grooms; Jafrā; Jerusalem (Palestine); Jihād; Leaders; Mījānā; Mothers; Poets; Sons; Wedding celebration; ʻAtābā; Ants; Children's stories; Dabkah; Death; Families; Goats; Hiding; Husbands; Hyenas; Income; Jafrā; Letters; Marriage; Mosques; Musical instruments; Poets; Prayers; Priests; Religious belief; Shepherds; Trade; Brides; Dabkah; Dance; Dinners and dinning; Grooms; Horseback riding; Lullabies; Poets; Shaykhs; Ululation; Wedding celebration; Wedding presents; Wedding veils; Women; Boys; Childbirth; Fāṭimah, -632 or 633; Happiness; Lullabies; Maqām; Medina (Saudi Arabia); Muḥammad, Prophet, 571-633, Prayers; Pilgrimage; Religious ceremonies; Ṣaḥābah; Ululation; Boys; Brides; Celebrations; Cities and towns; Clothing and dresses; Dabkah; Daughters-in-law; Engagement; Folk songs; Girls; Gold; Grooms; Ḥinnah; Honor; Hospitality; Marriage contracts; Marriage proposals; Mothers-in-law; Parents; Ululation; Wedding presents; Women dressmakers; Brides; Brothers; Clothing and dresses; Dabkah; Dietary practices; Fathers; Grooms; Helpfulness; Invitations; Jafrā; Men; Mothers; Musical instruments; Ululation; Uncles; Wedding preparations; Wedding veils; Barbers; Cooking; Dabkah; Dalʻūnā; Dance; Folk songs; Groom Shower; Grooms; Mothers; Musical instruments; Singing; Sisters; Yā Ghzayyil; Ẓarīf al-Ṭūl; ʻal-Rūzanā; Brides; Groom Shower; Horses; Men; Mothers; Women</dc:otherSubject>
  <dc:biography>سجلت المقابلة أيضا مع نمر علي عيسى، ذكر، ولد عام 1921 في حطين، فلسطين ويقيم في مخيم عين الحلوة للاجئين الفلسطنيين، لبنان.</dc:biography>
  <dc:biographyAR>سجلت المقابلة مع مريم فتح الله السعدي ، أنثى، ولدت عام 1932 في الزيب، فلسطين وتقبم في مخيم عين الحلوة للاجئين الفلسطنيين، لبنان.</dc:biographyAR>
  <dc:toc>Palestinian popular songs wedding songs 
. (@ 0:00)</dc:toc>
  <dc:tocAR>الأغاني الشعبية الفلسطينية وأغاني الأعراس. (@ 0:00)</dc:tocAR>
  <dc:toc>Folk tales and fables. (@ 29:43)</dc:toc>
  <dc:tocAR>الحكايات الشعبية والخرافات الحيوانية. (@ 29:43)</dc:tocAR>
  <dc:toc>Wedding customs and songs. (@ 44:47)</dc:toc>
  <dc:tocAR>أغاني وعادات العرس. (@ 44:47)</dc:tocAR>
  <dc:toc>Praise of Muḥammad . (@ 73:1)</dc:toc>
  <dc:tocAR>مديح النبي محمد. (@ 73:1)</dc:tocAR>
  <dc:toc>Marriage customs and rites. (@ 90:56)</dc:toc>
  <dc:tocAR>طقوس وعادات الزواج. (@ 90:56)</dc:tocAR>
  <dc:toc>Palestinian wedding songs and traditions . (@ 120:58)</dc:toc>
  <dc:tocAR>تقاليد وأغاني الأعراس الفلسطينية. (@ 120:58)</dc:tocAR>
  <dc:toc>Wedding songs and zaffah. (@ 146:13)</dc:toc>
  <dc:tocAR>أغاني العرس والزفة. (@ 146:13)</dc:tocAR>
  <dc:toc>Palestinian wedding folk songs. (@ 174:17)</dc:toc>
  <dc:tocAR>أغاني الأعراس الشعبية الفلسطينية. (@ 174:17)</dc:tocAR>
  <dc:description>Made available in DSpace on 2019-02-27T12:35:12Z (GMT). No. of bitstreams: 0
  Previous issue date: 1995</dc:description>
  <dc:date>1995-11</dc:date>
  <dc:issuedDate>1995</dc:issuedDate>
  <dc:createdDate>2017-07-31</dc:createdDate>
  <dc:availableDate>2019-02-27T12:35:12Z</dc:availableDate>
  <dc:accessionedDate>2019-02-27T12:35:12Z</dc:accessionedDate>
  <dc:date>yyyy-mm-dd</dc:date>
  <dc:type>Sound</dc:type>
  <dc:identifierURI>https://n2t.net/ark:/86073/b3h337?src=poha-oai</dc:identifierURI>
  <dc:identifierURL>https://libraries.aub.edu.lb/poha-viewer/render.php?cachefile=jf_0115_maryam_al-sadi.xml</dc:identifierURL>
  <dc:collectionName>POHA, Al-Jana, Folktales Collection</dc:collectionName>
  <dc:collectionNameAR>مجموعة الجنى : الحكايات الشعبية</dc:collectionNameAR>
  <dc:collectionID>38</dc:collectionID>
  <dc:localID>jf_0115</dc:localID>
  <dc:identifier>jf_0115_maryam_al-sadi.xml</dc:identifier>
  <dc:language>Arabic</dc:language>
  <dc:relation>POHA, Al-Jana, Folktales Collection</dc:relation>
  <dc:rights>0</dc:rights>
  <dc:rights>The copyright holder of this interview is the Nakba Archive, all rights reserved.</dc:rights>
  <dc:rights />
  <dc:format>audio</dc:format>
  <dc:duration>03:02:12</dc:duration>
  <dc:format>mp3</dc:format>
  <dc:village>al-Zīb</dc:village>
  <dc:villageAR>الزيب</dc:villageAR>
  <dc:village>Ḥiṭṭīn</dc:village>
  <dc:villageAR>حطّين</dc:villageAR>
  <dc:interviewee_delimited>Sadi, Maryam Fathallah|al-Sa‘dī, Maryam Fatḥallāh</dc:interviewee_delimited>
  <dc:interviewee_delimited>Isa, Nimir Ali|ʻĪsá, Nimir ʻAlī</dc:interviewee_delimited>
  <dc:village_delimited>Zib|al-Zīb</dc:village_delimited>
  <dc:village_delimited>Hittin|Ḥiṭṭīn</dc:village_delimited>
  <dc:hierarchy_browse>POHA, Al-Jana, Folktales Collection{{{_ID_}}}38</dc:hierarchy_browse>
  <dc:hierarchy_top_id>38</dc:hierarchy_top_id>
  <dc:hierarchy_top_title>POHA, Al-Jana, Folktales Collection</dc:hierarchy_top_title>
  <dc:hierarchy_top_titleAR>مجموعة الجنى : الحكايات الشعبية</dc:hierarchy_top_titleAR>
  <dc:hierarchy_parent_id>38</dc:hierarchy_parent_id>
  <dc:hierarchy_parent_title>POHA, Al-Jana, Folktales Collection</dc:hierarchy_parent_title>
  <dc:hierarchy_sequence>14</dc:hierarchy_sequence>
  <dc:is_hierarchy_id>4771</dc:is_hierarchy_id>
  <dc:is_hierarchy_title>مقابلة مع مريم فتح الله السعدي ونمر علي عيسى</dc:is_hierarchy_title>
  <dc:thumbnail>https://libraries.aub.edu.lb/poha-viewer/content/thumbnails/audio.jpg</dc:thumbnail>
</oai_dc:dc>