{"iiif_manifest": "https://figgy.princeton.edu/concern/scanned_resources/7fbe175a-a208-4864-a50a-36b8579699d3/manifest", "thumbnail": "https://iiif.princeton.edu/loris/figgy_prod/fb%2Fa3%2Ff7%2Ffba3f7fdce0341f6af7a1f60c47fc2e5%2Fintermediate_file.jp2/full/!200,150/0/default.jpg", "rendering": "http://arks.princeton.edu/ark:/88435/g732dc607", "description": "Ms. codex. Title from leaf 2a. Physical description: 16 lines per page; written in shikastah in black on blue glazed, laid European paper. Catchwords. Occasional staining. Origin: Likely early 19th century. Incipit: الحمد لله الذي مهد لنا طريق الاصلاح ... فيقول ... هذا کتاب جمعت فيه مسائل الحلال و الحرام", "author": ["Mujāhid, Muḥammad ibn ʻAlī, 1766 or 1767-1826 or 1827"], "abstract": ["Treatise on Shiʻite fiqh."], "alternative": ["Iṣlāḥ", "Iṣlāḥ al-ʻamal", "اصلاح", "اصلاح العمل"], "extent": ["122 leaves : paper ; 206 x 166 (163 x 109) mm bound to 209 x 170 mm"], "identifier": ["<a href='http://arks.princeton.edu/ark:/88435/g732dc607' alt='Identifier'>http://arks.princeton.edu/ark:/88435/g732dc607</a>"], "replaces": ["pudl0112/6122823"], "title": [{"@value": "كتاب اصلاح", "@language": "ara"}, {"@value": "Kitāb Iṣlāḥ", "@language": "ara-latn"}], "dlme_title_ara_arab": "كتاب اصلاح", "dlme_title_ara_latn": "Kitāb Iṣlāḥ", "provenance": ["On leaf 1a, waqf statement dated 1259 H [1843 or 1844]."], "dlme_provenance_en": "On leaf 1a, waqf statement dated 1259 H [1843 or 1844].", "creator": ["Mujāhid, Muḥammad ibn ʻAlī, 1766 or 1767-1826 or 1827", "مجاهد، محمد بن علي، 1766 or 1767-1826 or 1827"], "dlme_creator_ara_latn": "Mujāhid, Muḥammad ibn ʻAlī, 1766 or 1767-1826 or 1827", "dlme_creator_ara_arab": "مجاهد، محمد بن علي، 1766 or 1767-1826 or 1827", "date": ["1800-1825"], "language": ["Arabic"], "text_language": ["Arabic."], "local_identifier": ["p8336jg28q"], "publisher": ["[between 1800 and 1825?]"], "subject": ["Islamic law"], "binding_note": ["Limp black leather with blind-stamped central mandorla and pendants and blind-tooled fillets."], "source_metadata_identifier": ["6122823"], "call_number": ["Islamic Manuscripts, New Series no. 36", "Electronic Resource"], "member_of_collections": ["Princeton Digital Library of Islamic Manuscripts"]}