<record xmlns="http://www.openarchives.org/OAI/2.0/" xmlns:xsi="http://www.w3.org/2001/XMLSchema-instance"><header><identifier>b17774536</identifier><datestamp>1966-01-01</datestamp></header><metadata><oai_dc:dc xmlns:dc="http://purl.org/dc/elements/1.1/" xmlns:oai_dc="http://www.openarchives.org/OAI/2.0/oai_dc/" xsi:schemaLocation="http://www.openarchives.org/OAI/2.0/oai_dc/ http://www.openarchives.org/OAI/2.0/oai_dc.xsd"><dc:description>https://libraries.aub.edu.lb/xtf/data/bookreader/b17774536/thumb.jpg</dc:description><dc:rights>مجلة الآداب لصاحبها سماح إدريس</dc:rights><dc:source>الاداب : مجلة شهرية تعنى بشؤون الفكر . مج.14.ع.03 (1966) v.14 03 1966</dc:source><dc:subject>الحيدري ، بلند ، 1926-1996. عشرون الف قتيل- قصيدة</dc:subject><dc:subject>ابو ماضي ، ايليا ، 1889-1957. المساء - قصيدة</dc:subject><dc:subject>الحيدري ، بلند ، 1926-1996. صدى عذاب - قصيدة</dc:subject><dc:subject>الحيدري ، بلند ، 1926-1996. الى زنجي من الاباما - قصيدة</dc:subject><dc:subject>الحيدري ، بلند ، 1926-1996. موت شاعر - قصيدة</dc:subject><dc:subject>الحيدري ، بلند ، 1926-1996. كبرياء - قصيدة</dc:subject><dc:subject>الحيدري ، بلند ، 1926-1996. جئتم مع الفجر ‪[شعر]‬</dc:subject><dc:subject>الحيدري ، بلند ، 1926-1996. صراع - قصيدة</dc:subject><dc:subject>الحيدري ، بلند ، 1926-1996. ها انت - قصيدة</dc:subject><dc:subject>الحيدري ، بلند ، 1926-1996. اغاني المدينة الميتة شعر</dc:subject><dc:subject>الحيدري ، بلند ، 1926-1996 ، مؤلف. خفقة الطين</dc:subject><dc:subject>الشعر الثوري العربي -- تاريخ ونقد</dc:subject><dc:subject>الحيدري ، بلند ، 1926-1996. الرحلة الثامنة - قصيدة</dc:subject><dc:subject>الشعر العربي -- العراق -- القرن العشرون -- تاريخ ونقد</dc:subject><dc:subject>ابو ريشة ، عمر ، 1910-1990. مصرع فنان - قصيدة</dc:subject><dc:subject>ابو شبكة ، الياس ، 1903-1947. افاعي الفردوس - ديوان</dc:subject><dc:subject>الايقاع</dc:subject><dc:subject>الحيدري ، بلند ، 1926-1996. سميراميس - قصيدة</dc:subject><dc:subject>الحيدري ، بلند ، 1926-1996. جئتم مع الفجر- قصيدة</dc:subject><dc:subject>الشعر العربي -- تاريخ ونقد</dc:subject><dc:subject>الحيدري ، بلند ، 1926-1996. النهر الاسود - قصيدة</dc:subject><dc:subject>الحيدري ، بلند ، 1926-1996. اوديب - قصيدة</dc:subject><dc:subject>بريمون الاب</dc:subject><dc:subject>عقل ، سعيد ، 1912-</dc:subject><dc:subject>الحيدري ، بلند ، 1926-1996. سر - قصيدة</dc:subject><dc:subject>الحيدري ، بلند ، 1926-1996. حب قديم‬ - قصيدة</dc:subject><dc:subject>ابو شبكة ، الياس ، 1903-1947. شمشون - قصيدة</dc:subject><dc:subject>اليوت ، ت. س. (توماس ستورنز) ، ) 1888-1965</dc:subject><dc:subject>الحيدري ، بلند ، 1926-1996. عقم - قصيدة</dc:subject><dc:rights>الجامعة الاميركية في بيروت</dc:rights><dc:type>Text</dc:type><dc:date>1966</dc:date><dc:creator>عباس ، عبد الجبار</dc:creator><dc:title>بلند الحيدري</dc:title><dc:description>ص. 98-101، 157-159</dc:description><dc:language>ar</dc:language><dc:identifier>http://purl.org/aub/ul/do/b17774536?src=oai</dc:identifier></oai_dc:dc></metadata></record>