{"manifest": "https://cdm21044.contentdm.oclc.org/iiif/info/abidindino/3395/manifest.json", "id": "https://cdm21044.contentdm.oclc.org/iiif/info/abidindino/3395/manifest.json", "resource": "https://cdm21044.contentdm.oclc.org/digital/iiif/abidindino/3393/full/full/0/default.jpg", "profile": "http://iiif.io/api/image/2/level1.json", "iiif_format": "image/jpeg", "type": "Yazışma", "accession-number": "001/109", "title": "Basınköy, 25.12.1970 tarihli Abidin Dino'ya mektup", "language": "Türkçe", "creator": "Yaşar Kemal, 1922-2015", "date": "1970-12-25", "description": "Binboğalar Efsanesi Roman - Senaryo - Film - \"\"Menekşe İstasyonu\"\" - Arif Dino - Rasih Nuri İleri - Oğuz Akkan - Ker Babayef. Mektup.", "format": "JPEG", "url": "http://digital.sabanciuniv.edu/abidindino/mektup/3040200000720.pdf", "rights": "© Sabancı Üniversitesi Sakıp Sabancı Müzesi. Tüm hakları saklıdır.", "repository": "digitalSSM", "source": "<span>From: <a href=\"http://www.digitalssm.org/digital/collection/abidindino/id/3395\">Basınköy, 25.12.1970 tarihli Abidin Dino'ya mektup</a></span>", "context": "http://iiif.io/api/presentation/2/context.json"}