{"manifest": "https://figgy.princeton.edu/concern/scanned_resources/8f7dc0f5-00f7-4617-a76d-dae5c51303ab/manifest", "thumbnail": "https://iiif.princeton.edu/loris/figgy_prod/59%2F31%2Fc8%2F5931c8ee09c749908e8eedf559093533%2Fintermediate_file.jp2/full/!200,150/0/default.jpg", "description": "ff. 54 (mutil., breaks off in the letter sīn; the last two leaves belong to the letter mīm). 265 x 183; 190 x 125 mm. 25 lin. 15th cen. - on the margins additions and corrections by the authorʼs hand. Brockelmann, GAL, II, 44 (no. 7); S II, 32.", "author": ["Sakhāwī, Muḥammad ibn ʻAbd al-Raḥmān, 1427 or 8-1497"], "identifier": ["<a href='http://arks.princeton.edu/ark:/88435/zg64tp54x' alt='Identifier'>http://arks.princeton.edu/ark:/88435/zg64tp54x</a>"], "replaces": ["pudl0112/6263192"], "title": [{"@value": "al-Maqāṣid al-ḥasanah fī bayān kathīr min al-aḥādīth al-mushtahirah ʻalá al-alsinah", "@language": "ara"}], "type": ["Texts"], "creator": ["Sakhāwī, Muḥammad ibn ʻAbd al-Raḥmān, 1427 or 8-1497"], "date": ["1400-1499"], "language": ["Arabic"], "local_identifier": ["pjh345880m"], "subject": ["Hadith—Texts—Early works to 1800"], "source_metadata_identifier": ["6263192"], "call_number": ["Islamic Manuscripts, Garrett no. 277Y", "Electronic Resource"], "member_of_collections": ["Princeton Digital Library of Islamic Manuscripts"]}