{"id": "https://cdm21044.contentdm.oclc.org/iiif/info/Kitapvehat/170397/manifest.json", "resource": {"@id": "https://cdm21044.contentdm.oclc.org/digital/iiif/Kitapvehat/170373/full/full/0/default.jpg", "@type": "dctypes:Image", "service": {"@context": "http://iiif.io/api/image/2/context.json", "@id": "https://cdm21044.contentdm.oclc.org/digital/iiif/Kitapvehat/170373", "width": 3445, "height": 5306, "tiles": [{"width": 3445, "scaleFactors": [1, 2, 4, 8, 16]}], "profile": "http://iiif.io/api/image/2/level1.json", "protocol": "http://iiif.io/api/image"}, "format": "image/jpeg", "width": 3445, "height": 5306}, "tür_(type)": "Hat", "başlık_(title)": "Meşk murakkası", "dil_(language)": "Arapça", "hattat_(calligrapher)": "Hattatı bilinmiyor", "tarih_(date)": "19. yüzyıl", "boyutlar_(measurements)": "33 x 21,4 cm; 17 kıt'a", "yazı_cinsi_(script)": "Talik", "malzemeler_(materials)": "Âharlı ve ebrulu kâğıt üzerine siyah mürekkep ve altın", "açıklama_(description)": "Murakkada, düz, âharlı ve ebrulu, renkli kâğıtlar üzerine talik harflerin ve hecelerin alıştırmasından oluşan müfredat meşki (1-12. kıt’alar) ile besmelenin fazileti, Allah'ın büyüklüğü ve gücü, Hz. Muhammed'in vasıfları hakkındaki kısa metinlerden oluşan mürekkebat meşki (13-17. kıt’alar) yer alır. Eserin 13. ve 14. kıt’alarında Hakanî Mehmed Bey'in (ö. 1606) 1007/1598 yılında yazdığı, 716 beyitlik Türkçe Hilye-i Hakanî'den beyitler de vardır.  ", "tezhipler_(illuminations)": "Murakkaanın son yaprağında (y. 10a), \"Kadri\" damgalı kâğıt üzerine 19. yüzyıl üslubunda, içinde çiçekleriyle büyükçe bir vazo resmedilmiştir.", "ketebe_ve_zehebe_kaydı_(inscriptions)": "Kıt'aların yazılı olduğu kâğıtların alt köşeleri damgalıdır. 12-13. ve 15. kıt'alardaki, üzeri altın yaldızlanmış soğuk damga, 18. yüzyılın kâğıtçılarından Rifatî Efendi'ye aittir. 1- 2. kıt'alarda ise Kadri isimli bir diğer kâğıt ustasının damgası okunmaktadır.", "bulunduğu_yer_(current_location)": "Sabancı Üniversitesi Sakıp Sabancı Müzesi (Emirgan, İstanbul, Türkiye)", "envanter_numarası_(identifier)": "120-0379", "müzeye_geliş_şekli_(provenance)": "Sakıp Sabancı özel koleksiyonundan bağışlanmıştır.", "müzeye_geliş_tarihi_(provenance_date)": "2002", "telif_hakkı_(copyright)": "© Sabancı Üniversitesi Sakıp Sabancı Müzesi. Tüm hakları saklıdır.", "repository": "digitalSSM", "source": "<span>From: <a href=\"http://www.digitalssm.org/digital/collection/Kitapvehat/id/170397\">Meşk murakkası</a></span>", "context": "http://iiif.io/api/presentation/2/context.json"}