<record xmlns="http://www.openarchives.org/OAI/2.0/" xmlns:xsi="http://www.w3.org/2001/XMLSchema-instance"><header><identifier>81055/vdc_100000000282.0x0001cb_ar</identifier><datestamp>2018-04-18T05:27:54.117Z</datestamp></header><metadata><mods xmlns="http://www.loc.gov/mods/v3"><identifier>81055/vdc_100000000282.0x0001cb_ar</identifier><location><shelfLocator>IOR/R/15/2/1724</shelfLocator><url>http://www.qdl.qa/%D8%A7%D9%84%D8%B9%D8%B1%D8%A8%D9%8A%D8%A9/archive/81055/vdc_100000000282.0x0001cb</url><physicalLocation>المكتبة البريطانية: أوراق خاصة وسجلات من مكتب الهند</physicalLocation></location><recordInfo><recordIdentifer>IOR/R/15/2/1724</recordIdentifer></recordInfo><titleInfo><title>'الملف ٢٨\٢٦ I مراسلات متنوعة مع وبخصوص "كاسوك" (التي أعيدت تسميتها إلى AAOC)'</title></titleInfo><originInfo><dateIssued>1939/1948</dateIssued><dateCaptured>2014-05-30T00:14:41</dateCaptured></originInfo><language><languageTerm authority="iso639-2b">eng</languageTerm></language><physicalDescription><extent>ملف واحد (٥٦ ورقة)</extent><extent>الوثائق في الملف مرتبة ترتيبًا زمنيًا. توجد ملاحظات في نهاية الملف (الأوراق ٤٨-٥٣). تشير الملاحظات إلى الوثائق الموجودة بالملف؛ حيث تقدم وصفًا موجزًا للمراسلات برقم مرجعي يشير إلى تلك المراسلات في الملف.</extent><extent>ترقيم الأوراق بالقلم الرصاص في أعلى اليمين مع سطر تحت الأرقام في الأغلب. يبدأ الترقيم على الورقة الأولى بالأرقام ١، ١أ، ثم ٢-١٥؛ ١٦، ١٦أ، ١٦ب وينتهي على الصفحة الأخيرة بالرقم ٥٣.</extent></physicalDescription><abstract>يحتوي الملف على مراسلات بين شركة كاليفورنيا العربية للزيت القياسي (كاسوك) التي أعيدت تسميتها منذ عام ١٩٤٤ لتصبح شركة النفط العربية الأمريكية (AAOC) وممثلي شركة نفط البحرين المحدودة (بابكو) والوكيل السياسي في البحرين حول ظروف العمالة والتوظيف في البحرين.</abstract><typeOfResource>text</typeOfResource><name type="corporate"><namePart>شركة الزيت العربية الأمريكية</namePart><role><roleTerm type="text">correspondent</roleTerm></role></name><accessCondition type="Use and reproduction"><url>http://www.qdl.qa/%D8%A7%D9%84%D8%B9%D8%B1%D8%A8%D9%8A%D8%A9/archive/81055/vdc_100000000282.0x0001cb#share</url></accessCondition></mods></metadata></record>