<record xmlns="http://www.openarchives.org/OAI/2.0/" xmlns:xsi="http://www.w3.org/2001/XMLSchema-instance"><header><identifier>81055/vdc_100024052052.0x000018_ar</identifier><datestamp>2018-04-16T23:44:46.688Z</datestamp></header><metadata><mods xmlns="http://www.loc.gov/mods/v3"><identifier>81055/vdc_100024052052.0x000018_ar</identifier><location><shelfLocator>IOR/R/15/1/16, f 78</shelfLocator><url>http://www.qdl.qa/%D8%A7%D9%84%D8%B9%D8%B1%D8%A8%D9%8A%D8%A9/archive/81055/vdc_100024052052.0x000018</url><physicalLocation>المكتبة البريطانية: أوراق خاصة وسجلات من مكتب الهند</physicalLocation></location><recordInfo><recordIdentifer>IOR/R/15/1/16, f 78</recordIdentifer></recordInfo><titleInfo><title>رسالة من ويليام بروس، المقيم البريطاني في بوشهر، إلى أ. ألان، القائم بأعمال سكرتير مجلس الإشراف في كلكتا</title></titleInfo><originInfo><dateIssued>1815/1815</dateIssued><dateCaptured>2014-10-01T00:42:34</dateCaptured></originInfo><language><languageTerm authority="iso639-2b">eng</languageTerm></language><physicalDescription><extent>ورقة واحدة</extent></physicalDescription><accessCondition type="Use and reproduction"><url>http://www.qdl.qa/%D8%A7%D9%84%D8%B9%D8%B1%D8%A8%D9%8A%D8%A9/archive/81055/vdc_100024052052.0x000018#share</url></accessCondition></mods></metadata></record>