{"rendering": "https://digital.bodleian.ox.ac.uk/inquire/p/a936441f-8f37-43f2-be42-8022f58a63a2", "thumbnail": "https://iiif.bodleian.ox.ac.uk/iiif/image/440d073a-7f66-4cd9-9b0e-141654bf0a94/full/256,/0/default.jpg", "description_top": "Treatise on weaponry, commissioned by Saladin", "homepage": "<span><a href=\"https://digital.bodleian.ox.ac.uk/inquire/p/a936441f-8f37-43f2-be42-8022f58a63a2\">View on Digital Bodleian</a></span>", "catalogue_description": "<a href=\"https://www.fihrist.org.uk/catalog/manuscript_11111\">Fihrist: Union Catalogue of Manuscripts from the Islamicate World</a>", "title": "Treatise on weaponry, commissioned by Saladin", "shelfmark": "Bodleian Library MS. Huntington 264", "author": "[Saladin?]", "language": "Arabic", "description": "45C1:  weapons", "collection": "Arabic Manuscripts and Maps", "record_created": "2018-08-01T13:00:00Z", "holding_institution": "Bodleian Libraries, University of Oxford"}