{"thumbnail": "https://iiif.bodleian.ox.ac.uk/iiif/image/f650722f-5d31-4386-8949-69a6cd01c621/full/256,/0/default.jpg", "description": ".", "homepage": ">", "title": ["a", "l", "-", "K", "i", "t", "ā", "b", " ", "a", "l", "-", "M", "a", "n", "ṣ", "ū", "r", "ī", " ", "f", "ī", " ", "a", "l", "-", "ṭ", "i", "b", "b", " ", "(", "T", "h", "e", " ", "B", "o", "o", "k", " ", "o", "n", " ", "M", "e", "d", "i", "c", "i", "n", "e", " ", "f", "o", "r", " ", "a", "l", "-", "M", "a", "n", "ṣ", "ū", "r", ")"], "author": ")", "language": "c", "collection": "s", "record_created": "Z", "holding_institution": "d"}