{"rendering": "https://digital.bodleian.ox.ac.uk/inquire/p/1cb03db3-43ac-41b4-98e0-58c81144704d", "thumbnail": "https://iiif.bodleian.ox.ac.uk/iiif/image/ff6e17ee-3351-4a7c-a50d-66fb98a6e298/full/256,/0/default.jpg", "description_top": "Kyranides.", "homepage": "<span><a href=\"https://digital.bodleian.ox.ac.uk/inquire/p/1cb03db3-43ac-41b4-98e0-58c81144704d\">View on Digital Bodleian</a></span>", "catalogue_description": "<a href=\"https://www.fihrist.org.uk/catalog/manuscript_10231\">Fihrist: Union Catalogue of Manuscripts from the Islamicate World</a>", "title": "Kyranides.", "shelfmark": "Bodleian Library MS. Arab. d. 221", "author": "Hermes Trismegistus", "language": "Arabic", "date_statement": "14th century (?)", "description": "Collection of alchemical treatises.", "materials": "paper", "collection": "Images from 35mm Slides and Filmstrips", "digitization_project": "Medieval and Renaissance Manuscript Illumination (from 35mm)", "record_created": "2018-08-01T13:00:00Z", "holding_institution": "Bodleian Libraries, University of Oxford"}