{"thumbnail": "https://iiif.bodleian.ox.ac.uk/iiif/image/aab49109-4630-490d-a2d4-ff86795a9f43/full/256,/0/default.jpg", "description": "Common prayers, Romanian (Greek rite).", "homepage": "https://digital.bodleian.ox.ac.uk/inquire/p/1183bb8c-4788-4480-b6e4-4cf6ac8890c3", "title": "Common prayers, Romanian (Greek rite).", "date_statement": "1301–1400", "place_of_origin": "[Byzantium]", "collection": "Polonsky Foundation Digitization Project", "catalogue_identifier": "Neubauer 1144", "digitization_project": "The Polonsky Foundation Digitization Project (2012-2017)", "record_created": "2017-07-27T10:36:26Z", "holding_institution": "Bodleian Libraries, University of Oxford"}