{"thumbnail": "https://iiif.bodleian.ox.ac.uk/iiif/image/993e1752-e010-4306-be9d-803729155c45/full/256,/0/default.jpg", "description": ".", "homepage": ">", "title": ["C", "o", "l", "l", "e", "c", "t", "i", "o", "n", " ", "o", "f", " ", "k", "a", "b", "b", "a", "l", "i", "s", "t", "i", "c", " ", "t", "e", "x", "t", "s"], "author": "s", "language": "w", "date_statement": "6", "place_of_origin": ")", "collection": "t", "catalogue_identifier": "5", "digitization_project": ")", "record_created": "Z", "holding_institution": "d"}