{"rendering": "https://digital.bodleian.ox.ac.uk/inquire/p/4452c109-f425-46b6-b319-b65ccc61e721", "thumbnail": "https://iiif.bodleian.ox.ac.uk/iiif/image/bc4c7525-49e7-4904-882a-a082076ef367/full/256,/0/default.jpg", "description_top": "Zohar (Parashat Bereʼshit, with Moses Cordovero's commentary Or yaḳar)", "homepage": "<span><a href=\"https://digital.bodleian.ox.ac.uk/inquire/p/4452c109-f425-46b6-b319-b65ccc61e721\">View on Digital Bodleian</a></span>", "title": "Zohar (Parashat Bereʼshit, with Moses Cordovero's commentary Or yaḳar)", "shelfmark": "Bodleian Library MS. Oppenheim Add. fol. 2", "date_statement": "1591", "place_of_origin": "[Italy]", "collection": "Hebrew Manuscripts and Printed Books", "catalogue_identifier": "Neubauer 1560", "digitization_project": "The Polonsky Foundation Digitization Project (2012-2017)", "record_created": "2016-02-01T15:54:20Z", "holding_institution": "Bodleian Libraries, University of Oxford"}