{"rendering": "https://digital.bodleian.ox.ac.uk/inquire/p/4f2ea06f-050f-4125-a53a-9b69e2bc1569", "thumbnail": "https://iiif.bodleian.ox.ac.uk/iiif/image/cdcab143-3b8a-44c5-bbae-61c4740cae08/full/256,/0/default.jpg", "description_top": "Miscellany", "homepage": "<span><a href=\"https://digital.bodleian.ox.ac.uk/inquire/p/4f2ea06f-050f-4125-a53a-9b69e2bc1569\">View on Digital Bodleian</a></span>", "catalogue_description": "<a href=\"https://hebrew.bodleian.ox.ac.uk/catalog/manuscript_459\">Hebrew and Judaica Manuscripts at the Bodleian Libraries, Oxford University</a>", "title": "Miscellany", "shelfmark": "Bodleian Library MS. Reggio 47", "author": "Modena, Leone", "date_statement": "1499–1825", "description": "Contents: Ptolemy, Maʿaśeh keli ha-habaṭah (Treatise on the astrolabe) (ff. 1v-2v). Luḥot (f. 3). Tekhunat ha-kadur (ff. 4r-13v). Josef Ṭaṭtsiḳ, La-ʿaśot ha-atsṭrolabe (ff. 14v-17r). Jacob ben Machir Ibn Tibbon, Rovaʿ Yiśraʾel (\"Israel's Quadrant\", chapter 16) (f. 18v). Leone Modena, Sefer ben David (ff. 19r-24r). Simon Calimani, Ḳol Śimḥa (ff. 26-34).", "collection": "Hebrew Manuscripts and Printed Books", "catalogue_identifier": "Neubauer 2080", "digitization_project": "The Polonsky Foundation Digitization Project (2012-2017)", "record_created": "2016-02-12T11:56:14Z", "holding_institution": "Bodleian Libraries, University of Oxford"}