{"thumbnail": "https://iiif.bodleian.ox.ac.uk/iiif/image/d775f8f1-ba72-44a0-af01-d0d58fa6df97/full/256,/0/default.jpg", "description": "C o m m e n t a r y   o n   P r o v e r b s", "homepage": ">", "title": ["C", "o", "m", "m", "e", "n", "t", "a", "r", "y", " ", "o", "n", " ", "P", "r", "o", "v", "e", "r", "b", "s"], "author": "n", "date_statement": "5", "place_of_origin": "]", "collection": "t", "catalogue_identifier": "6", "digitization_project": ")", "record_created": "Z", "holding_institution": "d"}