{"rendering": "https://digital.bodleian.ox.ac.uk/inquire/p/aad4d64c-675f-4e0d-ace0-08a6289db033", "thumbnail": "https://iiif.bodleian.ox.ac.uk/iiif/image/7d6e0a2e-d8dc-4526-8d10-ad7e3aade38b/full/256,/0/default.jpg", "description_top": "Poetic miscellany", "homepage": "<span><a href=\"https://digital.bodleian.ox.ac.uk/inquire/p/aad4d64c-675f-4e0d-ace0-08a6289db033\">View on Digital Bodleian</a></span>", "title": "Poetic miscellany", "shelfmark": "Bodleian Library MS. Oppenheim Add. 4° 82", "author": "Ibn Ezra, Moses", "date_statement": "1276–1300", "place_of_origin": "[Orient]", "description": "Contents: Sefer ha-ʿanaḳ (ff. 2v-127r). Diṿan (ff. 127v-325v).", "collection": "Hebrew Manuscripts and Printed Books", "catalogue_identifier": "Neubauer 1972", "digitization_project": "The Polonsky Foundation Digitization Project (2012-2017)", "record_created": "2016-02-23T12:22:58Z", "holding_institution": "Bodleian Libraries, University of Oxford"}