{"rendering": "https://digital.bodleian.ox.ac.uk/inquire/p/c6789336-b555-4835-8545-2af62306c9fa", "thumbnail": "https://iiif.bodleian.ox.ac.uk/iiif/image/ea10684a-2f34-4324-b31c-6b83f5d660ea/full/256,/0/default.jpg", "description_top": "Sefer Malmad ha-Talmidim", "homepage": "<span><a href=\"https://digital.bodleian.ox.ac.uk/inquire/p/c6789336-b555-4835-8545-2af62306c9fa\">View on Digital Bodleian</a></span>", "title": "Sefer Malmad ha-Talmidim", "shelfmark": "Bodleian Library MS. Huntington 454", "author": "Anatoli, Jacob ben Abba Mari ben Samson", "language": "Hebrew", "date_statement": "1375–1400", "place_of_origin": "[Italy]", "description": "Incomplete. Contains also fragments from Baḥya ben Joseph ibn Paḳuda's Al-Hidāja ʼilā farāʼid al-qulūb (The book of direction to the duties of the heart) together with an extract from a homily by a different author and  a liturgy by Levi ben Moses.", "collection": "Hebrew Manuscripts and Printed Books", "catalogue_identifier": "Neubauer 981", "digitization_project": "The Polonsky Foundation Digitization Project (2012-2017)", "record_created": "2017-02-23T08:55:06Z", "holding_institution": "Bodleian Libraries, University of Oxford"}