{"manifest": "https://figgy.princeton.edu/concern/scanned_resources/d057098d-9f27-4cb7-a31c-ad5278cb9c62/manifest", "thumbnail": "https://iiif.princeton.edu/loris/figgy_prod/6b%2F02%2F9e%2F6b029e91edee46748c3dabcf6d51b0ae%2Fintermediate_file.jp2/full/!200,150/0/default.jpg", "director": [{"@value": "نيازي مصطفى", "@language": "ara-arab"}], "date_created": ["1977"], "extent": ["1 piece."], "genre": ["Posters"], "identifier": ["ark:/88435/ng451j810"], "resource_type": ["still image"], "title": [{"@value": "اذكياء ولكن اغبياء", "@language": "ara-arab"}], "language": ["ara"], "local_identifier": ["eg1-0046"], "geographic_origin": ["Egypt"], "member_of_collections": ["Middle Eastern Film Posters Digitization Initiative", "Selections from the Near East Collections"], "rendered_actors": ["رشدي اباظة", "عادل امام", "سمير غانم"]}