{"manifest": "https://figgy.princeton.edu/concern/scanned_resources/d8ac6484-c4fb-4247-9fe5-7e8d06bf19a9/manifest", "thumbnail": "https://iiif.princeton.edu/loris/figgy_prod/fd%2F6c%2Fde%2Ffd6cdeb178604e07ab5e1ebcd551cd68%2Fintermediate_file.jp2/full/!200,150/0/default.jpg", "director": [{"@value": "حسن احمد", "@language": "ara-arab"}], "date_created": ["2005"], "extent": ["1 piece."], "genre": ["Posters"], "identifier": ["ark:/88435/00000135p"], "resource_type": ["still image"], "title": [{"@value": "السيد ابو العربي وصل", "@language": "ara-arab"}], "language": ["ara"], "local_identifier": ["eg1-0290"], "geographic_origin": ["Egypt"], "member_of_collections": ["Middle Eastern Film Posters Digitization Initiative", "Selections from the Near East Collections"], "rendered_actors": ["هاني رمزي", "منى شلبي", "ليلى", "صلاح عبد الله"]}