{"manifest": "https://figgy.princeton.edu/concern/scanned_resources/1858a395-8538-489a-9d66-479aff7684fd/manifest", "thumbnail": "https://iiif.princeton.edu/loris/figgy_prod/1a%2F70%2Fe3%2F1a70e35b596642fdb286b71c4a388595%2Fintermediate_file.jp2/full/!200,150/0/default.jpg", "identifier": ["ark:/88435/m613mz86r"], "resource_type": ["still image"], "title": [{"@value": "جوز مراتي", "@language": "ara-arab"}], "local_identifier": ["eg1-0658"], "member_of_collections": ["Middle Eastern Film Posters Digitization Initiative", "Selections from the Near East Collections"]}