{"manifest": "https://figgy.princeton.edu/concern/scanned_resources/5e909188-5168-4960-95ae-d4ebc27cc253/manifest", "thumbnail": "https://iiif.princeton.edu/loris/figgy_prod/50%2Fc5%2F59%2F50c559db716445e283210f4d51f7ed32%2Fintermediate_file.jp2/full/!200,150/0/default.jpg", "director": [{"@value": "Salmān, Muḥammad", "@language": "ara-latn"}, {"@value": "محمد سلمان", "@language": "ara-arab"}], "date_created": ["1901 - 2000"], "extent": ["1 piece."], "genre": ["Posters"], "identifier": ["ark:/88435/0g354g54h"], "resource_type": ["still image"], "title": [{"@value": "موال", "@language": "ara-arab"}], "language": ["ara"], "local_identifier": ["le1-0125"], "member_of_collections": ["Middle Eastern Film Posters Digitization Initiative", "Selections from the Near East Collections"], "rendered_actors": ["Ṣabāḥ", "صباح", "Ṣāfī, Wadīʻ", "وديع الصافي", "وحيد جلال"]}