{"manifest": "https://figgy.princeton.edu/concern/scanned_resources/b8023503-bf9f-4692-a7f3-317d700964b1/manifest", "thumbnail": "https://iiif.princeton.edu/loris/figgy_prod/bf%2Fe1%2Fb3%2Fbfe1b3cc3ed7493bb6224a90c81a8107%2Fintermediate_file.jp2/full/!200,150/0/default.jpg", "director": [{"@value": "مدحت السباعي", "@language": "ara-arab"}], "date_created": ["1991"], "extent": ["1 piece."], "genre": ["Posters"], "identifier": ["ark:/88435/2j62s6170"], "resource_type": ["still image"], "title": [{"@value": "ثلاثة علي مائدة الدم", "@language": "ara-arab"}], "language": ["ara"], "local_identifier": ["eg1-0633"], "geographic_origin": ["Egypt"], "member_of_collections": ["Middle Eastern Film Posters Digitization Initiative", "Selections from the Near East Collections"], "rendered_actors": ["الهام شاهين", "محمود ياسين", "سعيد صالح"]}