{"manifest": "https://cdm15795.contentdm.oclc.org/iiif/info/p15795coll19/157/manifest.json", "id": "https://cdm15795.contentdm.oclc.org/iiif/info/p15795coll19/157/manifest.json", "resource": "https://cdm15795.contentdm.oclc.org/digital/iiif/p15795coll19/157/full/full/0/default.jpg", "profile": "http://iiif.io/api/image/2/level1.json", "iiif_format": "image/jpeg", "title-english": "Communist Imperialism", "title-arabic": "الاستعمار الشيوعي", "creator": "Shafik, Doria", "date": "1957-05", "publisher": "Bint al-Nil", "description-english": "In this article, Doria Shafik sounds the alarm on the looming threat of international communism and its attempts to invade the Arab East. Special reference is made to what happened in Communist Hungary where legitimate claims for freedom were met with violent suppression.", "description-arabic": "تحذر كاتبة المقالة من الخطر الاستعماري الذي تشكله الشيوعية الدولية ومحاولاتها التغلغل في الشرق العربي، مشيرة إلى ما حدث في المجر وهو بلد شيوعي حينما طالب بقسط من الحريات فاستعملت معه أشد وسائل العنف.", "subject": "Women's rights -- Egypt; Women -- Arab countries -- Periodicals", "language": "Arabic", "type": "Still Image; Text", "format": "image/jpeg", "genre-aat": "Article", "source": "<span>From: <a href=\"http://digitalcollections.aucegypt.edu/digital/collection/p15795coll19/id/157\">Communist Imperialism</a></span>", "rights": "Women and Memory Forum are copyright holders of the Bint al-Nil Journal Collection.", "repository": "Rare Books and Special Collections Digital Library", "context": "http://iiif.io/api/presentation/2/context.json"}