{"manifest": "https://cdm15795.contentdm.oclc.org/iiif/info/p15795coll11/3460/manifest.json", "id": "https://cdm15795.contentdm.oclc.org/iiif/info/p15795coll11/3460/manifest.json", "resource": "https://cdm15795.contentdm.oclc.org/digital/iiif/p15795coll11/3456/full/full/0/default.jpg", "profile": "http://iiif.io/api/image/2/level1.json", "iiif_format": "image/jpeg", "title": "Safiya Zaghloul glass plate negatives", "date": "1934", "location": "Egypt", "description": "Glass plate negatives of Egyptian political activist Safiya Zaghloul from the Mostafa Amin Collection. Zaghloul, known as the \"Mother of the Egyptians\" (أم المصريين), was a leader of the Wafd party, and wife of Egyptian revolutionary and politician Saad Zaghloul. The photos may have been taken in the mid-1930s. ", "subject": "Zaghloul, Safia, 1876-1946", "type": "Still image", "format": "image/jpeg", "genre-aat": "glass plate negatives", "collection": "Mostafa Amin Collection", "source": "<span>From: <a href=\"http://digitalcollections.aucegypt.edu/digital/collection/p15795coll11/id/3460\">Safiya Zaghloul glass plate negatives</a></span>", "rights": "Copyright the American University in Cairo, 2019", "repository": "Rare Books and Special Collections Digital Library", "context": "http://iiif.io/api/presentation/2/context.json"}